{"timestamp": 1773735091.4347472, "keyword": "IT company", "location": "Indore", "cell_idx": 177, "results": [{"place_id": "0x3963179ba819d679:0x97d67928bba81e05", "name": "ITGeeks Technologies Pvt. Ltd.", "category": "Software company", "street": "ITGeeks Technologies Pvt. Ltd", "city": "02, Yamuna nagar", "phone": "09179880603", "website": "http://www.itgeeks.com/", "rating": 4.6, "review_count": "", "latitude": 22.9538781, "longitude": 76.03808699999999, "maps_url": "https://www.google.com/maps/place/?q=place_id:0x3963179ba819d679:0x97d67928bba81e05"}, {"place_id": "0x3963179ca584a047:0xba87fc574f813753", "name": "Xlligent Softwares Pvt Ltd", "category": "Software company", "street": "111", "city": "near front of DCB Bank", "phone": "06261900209", "website": "https://www.xlligent-softwares.com/", "rating": 4.9, "review_count": "", "latitude": 22.9666632, "longitude": 76.0492101, "maps_url": "https://www.google.com/maps/place/?q=place_id:0x3963179ca584a047:0xba87fc574f813753"}, {"place_id": "0x396317edff48b3f5:0xc5c058b66ca61b0c", "name": "OminiFlow Enterprises - WhatsApp Api Provider, ChatBot, RealState lead Automation, Business Growth", "category": "Software company", "street": "18", "city": "Kalani Bagh, Tarani Colony, Pachunkar Colony, Ram Nagar", "phone": "09755332357", "website": "", "rating": 4.9, "review_count": "", "latitude": 22.962981799999998, "longitude": 76.0456596, "maps_url": "https://www.google.com/maps/place/?q=place_id:0x396317edff48b3f5:0xc5c058b66ca61b0c"}, {"place_id": "0x3963171787e17b59:0x307a92533e921d11", "name": "Edithtech Softwares", "category": "Software company", "street": "44", "city": "Shourya Complex", "phone": "09109260321", "website": "https://edithtechsoftwares.com/", "rating": 4.8, "review_count": "", "latitude": 22.9547074, "longitude": 76.0365456, "maps_url": "https://www.google.com/maps/place/?q=place_id:0x3963171787e17b59:0x307a92533e921d11"}, {"place_id": "0x39631780e5eb3c53:0xfc15871ccdfd3ccb", "name": "PebblePot Technologies Private Limited", "category": "Software company", "street": "04 Harshal Manglik Bhawan", "city": "AB Rd", "phone": "07898661161", "website": "https://www.pebblepot.in/", "rating": 4.7, "review_count": "", "latitude": 22.966351799999998, "longitude": 76.0499313, "maps_url": "https://www.google.com/maps/place/?q=place_id:0x39631780e5eb3c53:0xfc15871ccdfd3ccb"}, {"place_id": "0x39631772fb57fa4d:0x1aeaaccddfab1b64", "name": "ITWEBINFO", "category": "Software company", "street": "103", "city": "Shivaji Nagar, Moti Bunglow", "phone": "07582995555", "website": "http://itwebinfo.com/", "rating": 5, "review_count": "", "latitude": 22.9710605, "longitude": 76.0480532, "maps_url": "https://www.google.com/maps/place/?q=place_id:0x39631772fb57fa4d:0x1aeaaccddfab1b64"}, {"place_id": "0x396302b379920c87:0xae77c7696c44f45c", "name": "JTG_TECHNOLAB", "category": "Software company", "street": "40, Karoli nagar", "city": "near Kela Mata temple", "phone": "07974666953", "website": "https://jtgtechnolab.com/", "rating": 5, "review_count": "", "latitude": 22.9583767, "longitude": 76.0352805, "maps_url": "https://www.google.com/maps/place/?q=place_id:0x396302b379920c87:0xae77c7696c44f45c"}, {"place_id": "0x3963178ff220a477:0x1f25eae0f1ef5a7d", "name": "Himanshu Softtech", "category": "Software company", "street": "4-A , agroha nagar , AB road", "city": "Dewas, Madhya Pradesh 455001", "phone": "09425919122", "website": "http://www.himanshusofttech.com/", "rating": 4.7, "review_count": "", "latitude": 22.9619793, "longitude": 76.0464191, "maps_url": "https://www.google.com/maps/place/?q=place_id:0x3963178ff220a477:0x1f25eae0f1ef5a7d"}, {"place_id": "0x3963178ff220a477:0x51910ecd6deaed53", "name": "Cyber Elite Pvt Ltd.", "category": "Software company", "street": "226 LIG", "city": "Jawahar Nagar, Gomti Nagar", "phone": "07089899090", "website": "https://cyberelite.in/", "rating": 4.2, "review_count": "", "latitude": 22.953131199999998, "longitude": 76.0426221, "maps_url": "https://www.google.com/maps/place/?q=place_id:0x3963178ff220a477:0x51910ecd6deaed53"}, {"place_id": "0x3963172b725b9649:0xca9958ddaa36af60", "name": "PixelNX", "category": "Software company", "street": "03", "city": "Bhartiya Grah Nirman Colony, Shivaji Nagar, Moti Bunglow", "phone": "09685829300", "website": "http://www.pixelnx.com/", "rating": 4.6, "review_count": "", "latitude": 22.967811299999997, "longitude": 76.0457447, "maps_url": "https://www.google.com/maps/place/?q=place_id:0x3963172b725b9649:0xca9958ddaa36af60"}, {"place_id": "0x39631792ea7d9083:0xc90228718db1b1af", "name": "Sypnosis Technologies - IT Company.", "category": "Software company", "street": "2nd Floor", "city": "10", "phone": "09039239604", "website": "https://sypnosistechnologies.com/", "rating": "", "review_count": "", "latitude": 22.955443499999998, "longitude": 76.0369978, "maps_url": "https://www.google.com/maps/place/?q=place_id:0x39631792ea7d9083:0xc90228718db1b1af"}, {"place_id": "0x396317226b2c42df:0x47098e396f961017", "name": "Expound Coderz Private Limited", "category": "Software company", "street": "267", "city": "Ram Nagar Extension, Mishrilal Nagar, Ganga Nagar", "phone": "07415752727", "website": "https://expoundcoderz.com/", "rating": 4.8, "review_count": "", "latitude": 22.9577816, "longitude": 76.0379663, "maps_url": "https://www.google.com/maps/place/?q=place_id:0x396317226b2c42df:0x47098e396f961017"}, {"place_id": "0x396317c3b78fb617:0xcad69c162e743e9", "name": "Farflung Technologies Pvt ltd", "category": "Software company", "street": "3 A", "city": "Pachunkar Colony, Panchsheel Nagar", "phone": "", "website": "https://farflungtechnologies.com/", "rating": 5, "review_count": "", "latitude": 22.9624773, "longitude": 76.0426938, "maps_url": "https://www.google.com/maps/place/?q=place_id:0x396317c3b78fb617:0xcad69c162e743e9"}, {"place_id": "0x3963177600d4efb5:0x33c81c908e54629c", "name": "Soham Web Solution - Web Development Company", "category": "Software company", "street": "Chamunda Complex", "city": "12, Civil Line", "phone": "07748018188", "website": "http://sohamsolution.com/", "rating": 4, "review_count": "", "latitude": 22.9648902, "longitude": 76.0480299, "maps_url": "https://www.google.com/maps/place/?q=place_id:0x3963177600d4efb5:0x33c81c908e54629c"}, {"place_id": "0x396317db662392a1:0xf724452f8057917", "name": "Evolve WebInfo Pvt.Ltd.", "category": "Software company", "street": "2nd Floor, Dewas Central, 314", "city": "AB Rd", "phone": "09926877335", "website": "http://evolvewebinfo.in/", "rating": 4.9, "review_count": "", "latitude": 22.9566475, "longitude": 76.0369968, "maps_url": "https://www.google.com/maps/place/?q=place_id:0x396317db662392a1:0xf724452f8057917"}, {"place_id": "0x39631781f7b0a2a7:0xe3e4f6269a463f9d", "name": "Hostihelp", "category": "Software company", "street": "237 SunCity 1", "city": "AB Rd", "phone": "09755688860", "website": "http://hostihelpservices.epizy.com/", "rating": 4.9, "review_count": "", "latitude": 22.9460408, "longitude": 76.02948649999999, "maps_url": "https://www.google.com/maps/place/?q=place_id:0x39631781f7b0a2a7:0xe3e4f6269a463f9d"}, {"place_id": "0x39631736a0f7d871:0xf0f334accf365a3a", "name": "Ayat infotech", "category": "Software company", "street": "51", "city": "Anand nagar, Itawa", "phone": "09589981295", "website": "http://ayatinfotech.com/", "rating": 5, "review_count": "", "latitude": 22.9726128, "longitude": 76.05058269999999, "maps_url": "https://www.google.com/maps/place/?q=place_id:0x39631736a0f7d871:0xf0f334accf365a3a"}, {"place_id": "0x3963177f0bb72c01:0x7dc0fc1caf36fcb", "name": "Adroit Technosoft", "category": "Software company", "street": "2nd floor, sri sawariya complex", "city": "AB Rd", "phone": "09713000193", "website": "https://adroittechnosoft.in/", "rating": 4.3, "review_count": "", "latitude": 22.9666878, "longitude": 76.0494731, "maps_url": "https://www.google.com/maps/place/?q=place_id:0x3963177f0bb72c01:0x7dc0fc1caf36fcb"}, {"place_id": "0x39630239f26f44ff:0x9990e42765534532", "name": "Hybrid Infotech Pvt Ltd", "category": "Software company", "street": "Forest colony, Shivaji Nagar, Moti Bunglow", "city": "Dewas, Madhya Pradesh 455001", "phone": "09993031042", "website": "http://hybridinfotech.com/", "rating": 5, "review_count": "", "latitude": 22.9662243, "longitude": 76.0484005, "maps_url": "https://www.google.com/maps/place/?q=place_id:0x39630239f26f44ff:0x9990e42765534532"}, {"place_id": "0x39631d62557ed507:0x5dc2b67a2ba7971a", "name": "Royal IT Service - IT Company in Indore", "category": "Software company", "street": "426 Scheme No. 114 Part 2", "city": "Anurag Nagar Ln", "phone": "09285192850", "website": "http://royalitservice.com/", "rating": 4.3, "review_count": "", "latitude": 22.7622528, "longitude": 75.9022899, "maps_url": "https://www.google.com/maps/place/?q=place_id:0x39631d62557ed507:0x5dc2b67a2ba7971a"}, {"place_id": "0x39631da0239602ff:0xa13448656bdbfa7a", "name": "Softsnare Technologies | IT Company | Software Company in Indore", "category": "Software company", "street": "R-353", "city": "Sector R, Mahalaxmi Nagar", "phone": "06264741175", "website": "http://www.softsnare.com/", "rating": 4.6, "review_count": "", "latitude": 22.758209299999997, "longitude": 75.9096251, "maps_url": "https://www.google.com/maps/place/?q=place_id:0x39631da0239602ff:0xa13448656bdbfa7a"}, {"place_id": "0x3963179aa37da85d:0x9ad74f985a500d01", "name": "Webstrot Technology", "category": "Software company", "street": "3rd Floor", "city": "Rathor Tower", "phone": "08827113366", "website": "https://www.webstrot.com/", "rating": 4.9, "review_count": "", "latitude": 22.960082, "longitude": 76.04385529999999, "maps_url": "https://www.google.com/maps/place/?q=place_id:0x3963179aa37da85d:0x9ad74f985a500d01"}, {"place_id": "0x3963173c14b63e79:0x65b66e0752b01a8c", "name": "Techconqueror \u2013 Software & IT Services", "category": "Software company", "street": "528 EWS", "city": "Mukherjee Nagar, Anukul Nagar", "phone": "08982396663", "website": "https://techconqueror.com/", "rating": 4.9, "review_count": "", "latitude": 22.971609599999997, "longitude": 76.0386747, "maps_url": "https://www.google.com/maps/place/?q=place_id:0x3963173c14b63e79:0x65b66e0752b01a8c"}, {"place_id": "0x396317745f3b0dad:0x2026d44c9c4f16dd", "name": "Netvertix Technologies", "category": "Software company", "street": "Padam Mohan Colony", "city": "8/2, BNP Rd", "phone": "09131332762", "website": "https://netvertixtechnologies.com/", "rating": 5, "review_count": "", "latitude": 22.9788064, "longitude": 76.0552076, "maps_url": "https://www.google.com/maps/place/?q=place_id:0x396317745f3b0dad:0x2026d44c9c4f16dd"}, {"place_id": "0x2d1fb13b66f9b3b9:0xd8d6782015bc63e4", "name": "Dharmdesigner IT Services", "category": "Internet marketing service", "street": "Silver Park", "city": "Balaji Nagar", "phone": "08120348239", "website": "https://dharmdesigner.com/", "rating": 5, "review_count": "", "latitude": 22.947556799999997, "longitude": 76.05479059999999, "maps_url": "https://www.google.com/maps/place/?q=place_id:0x2d1fb13b66f9b3b9:0xd8d6782015bc63e4"}, {"place_id": "0x396317fb8085a529:0x6218c068e21409af", "name": "Caplers Solutions Dewas", "category": "Software company", "street": "Station Rd", "city": "in front of 52 Dukaan", "phone": "07415119928", "website": "https://caplers.com/", "rating": 5, "review_count": "", "latitude": 22.9715527, "longitude": 76.0550499, "maps_url": "https://www.google.com/maps/place/?q=place_id:0x396317fb8085a529:0x6218c068e21409af"}, {"place_id": "0x396317edb498db2d:0x820ff94014864b5b", "name": "Active Now Tech", "category": "Software company", "street": "Mahalaxmi Nagar", "city": "09", "phone": "08839779337", "website": "https://activenow.in/", "rating": 5, "review_count": "", "latitude": 22.9575802, "longitude": 76.0409086, "maps_url": "https://www.google.com/maps/place/?q=place_id:0x396317edb498db2d:0x820ff94014864b5b"}, {"place_id": "0x3962e2ce8d0c8e49:0xdc163b3f996ee4c", "name": "NWAY Technologies Pvt. Ltd. | Best ERP Software in Indore | ERP Software in Indore | Construction ERP Software in India", "category": "Software company", "street": "Solitaire Park", "city": "298", "phone": "", "website": "https://www.nwayerp.com/", "rating": 4.5, "review_count": "", "latitude": 22.7593633, "longitude": 75.9380312, "maps_url": "https://www.google.com/maps/place/?q=place_id:0x3962e2ce8d0c8e49:0xdc163b3f996ee4c"}, {"place_id": "0x3962e2ce2f47899b:0x9f44070e6f8cca45", "name": "Techwave IT Solutions Pvt Ltd", "category": "Software company", "street": "Bhopal Motors JCB", "city": "near Panchvati", "phone": "09009155444", "website": "http://techwaveitsolutions.com/", "rating": 4.6, "review_count": "", "latitude": 22.7920648, "longitude": 75.9074073, "maps_url": "https://www.google.com/maps/place/?q=place_id:0x3962e2ce2f47899b:0x9f44070e6f8cca45"}, {"place_id": "0x3963179b47845d21:0x3c484352310d1dfd", "name": "Projection (Training & Placement Company)", "category": "Software Training Institute", "street": "05, Shayam Plaza, Patwardhan marg, Just", "city": "behind Grace Church", "phone": "09617569993", "website": "https://www.projectiononline.com/", "rating": 4.7, "review_count": "", "latitude": 22.967597899999998, "longitude": 76.050913, "maps_url": "https://www.google.com/maps/place/?q=place_id:0x3963179b47845d21:0x3c484352310d1dfd"}, {"place_id": "0x3962fdc27594b36f:0xf1f29e4d59089c17", "name": "Rubik Corner IT Services and Consultants", "category": "Website designer", "street": "5/1 Ramchandra Nagar Extension", "city": "Madhya Pradesh 455001", "phone": "09691665576", "website": "", "rating": 5, "review_count": "", "latitude": 22.945536999999998, "longitude": 76.0402613, "maps_url": "https://www.google.com/maps/place/?q=place_id:0x3962fdc27594b36f:0xf1f29e4d59089c17"}, {"place_id": "0x396317170221cccd:0xdc916aeffd9100ea", "name": "Webaashi Technologies", "category": "Software company", "street": "C 82, AB Rd", "city": "Kalani Bagh, Agroha Nagar, Gomti Nagar", "phone": "", "website": "http://webaashi.com/", "rating": 4.9, "review_count": "", "latitude": 22.9586091, "longitude": 76.0484482, "maps_url": "https://www.google.com/maps/place/?q=place_id:0x396317170221cccd:0xdc916aeffd9100ea"}, {"place_id": "0x3963179e783f3caf:0x370c4af9c04c7225", "name": "Satisfaction Web Solution Pvt. Ltd", "category": "Software company", "street": "146 Alkapuri", "city": "behind Shri Munisuvrat Swami Shwetambar Jain Mandir Dewas", "phone": "09826073695", "website": "http://www.satisfactionwebsolution.com/", "rating": 4.4, "review_count": "", "latitude": 22.967319, "longitude": 76.0412837, "maps_url": "https://www.google.com/maps/place/?q=place_id:0x3963179e783f3caf:0x370c4af9c04c7225"}, {"place_id": "0x3962fd40a62b9225:0x1dcbe63ab6cdfa6b", "name": "ThirdEssential IT Solutions Pvt. Ltd.", "category": "Software company", "street": "SR Villa", "city": "155, MR-1", "phone": "09993344255", "website": "http://www.thirdessential.com/", "rating": 4.2, "review_count": "", "latitude": 22.7540998, "longitude": 75.9129564, "maps_url": "https://www.google.com/maps/place/?q=place_id:0x3962fd40a62b9225:0x1dcbe63ab6cdfa6b"}, {"place_id": "0x396317d794e16759:0x4060a0afc2cc5781", "name": "Webniya Infotech", "category": "Software company", "street": "", "city": "", "phone": "", "website": "https://www.webniya.tech/", "rating": 5, "review_count": "", "latitude": 21.0680074, "longitude": 82.7525294, "maps_url": "https://www.google.com/maps/place/?q=place_id:0x396317d794e16759:0x4060a0afc2cc5781"}, {"place_id": "0x396317f6bce105ad:0x1b97ddd1edb96f8a", "name": "TechMac Digital Solutions", "category": "Software company", "street": "05 M.I.G, Ujjain Rd", "city": "near Water Tank", "phone": "08982878781", "website": "https://techmacdigital.com/", "rating": 4.7, "review_count": "", "latitude": 22.977732099999997, "longitude": 76.0322268, "maps_url": "https://www.google.com/maps/place/?q=place_id:0x396317f6bce105ad:0x1b97ddd1edb96f8a"}, {"place_id": "0x396317929f6eb6ff:0xd309788e3f800c63", "name": "Lumic technologies", "category": "Software company", "street": "28, Sardar Patel Marg", "city": "Sutar Bakhal, Old Town, Gomti Nagar", "phone": "07804920240", "website": "http://www.lumicsoft.com/", "rating": "", "review_count": "", "latitude": 22.9654703, "longitude": 76.0527128, "maps_url": "https://www.google.com/maps/place/?q=place_id:0x396317929f6eb6ff:0xd309788e3f800c63"}, {"place_id": "0x3963195684ca1f2d:0x616742ba66d094a3", "name": "Jadhav SoftTech", "category": "Software company", "street": "Balaji Dham", "city": "69", "phone": "", "website": "http://www.jadhavsofttech.com/", "rating": "", "review_count": "", "latitude": 22.9452684, "longitude": 76.0460969, "maps_url": "https://www.google.com/maps/place/?q=place_id:0x3963195684ca1f2d:0x616742ba66d094a3"}, {"place_id": "0x396317cb7c6c3d3b:0x9f2bbbfa9937c9b", "name": "SOMTARA Infotech", "category": "Software company", "street": "TARA KUNJ 205", "city": "opp. Escort Junior College", "phone": "", "website": "https://www.somtarainfotech.com/", "rating": "", "review_count": "", "latitude": 22.954623599999998, "longitude": 76.0349313, "maps_url": "https://www.google.com/maps/place/?q=place_id:0x396317cb7c6c3d3b:0x9f2bbbfa9937c9b"}, {"place_id": "0x3962fd3a65855555:0x6374d2fd9460384c", "name": "Dai Software Solution", "category": "Software company", "street": "Highlight House", "city": "507, MR-5", "phone": "09826356926", "website": "https://www.daisoftware.com/", "rating": 4, "review_count": "", "latitude": 22.7597479, "longitude": 75.9112177, "maps_url": "https://www.google.com/maps/place/?q=place_id:0x3962fd3a65855555:0x6374d2fd9460384c"}, {"place_id": "0x6cfaa7c055002bd5:0x9543a5812d93766", "name": "Updevix \u2013 Web & App Development Company", "category": "Software company", "street": "software Employment Ofiice", "city": "1st floor, Updevix \u2013 Web & App Development Company", "phone": "", "website": "https://www.updevix.com/", "rating": 5, "review_count": "", "latitude": 22.967655699999998, "longitude": 76.0543464, "maps_url": "https://www.google.com/maps/place/?q=place_id:0x6cfaa7c055002bd5:0x9543a5812d93766"}, {"place_id": "0x396318244daf11b5:0xc4a7dcfa7008013d", "name": "Bappa Creation India : Video Advertising Company", "category": "Video production service", "street": "Balgarh, balaji nagar, Industrial Area No.2, Dewas, Madhya Pradesh 455111", "city": "Dewas, Madhya Pradesh 455001", "phone": "08602895443", "website": "https://bappacreationindia.wixsite.com/bappacreationindia", "rating": 5, "review_count": "", "latitude": 22.9429922, "longitude": 76.05390899999999, "maps_url": "https://www.google.com/maps/place/?q=place_id:0x396318244daf11b5:0xc4a7dcfa7008013d"}, {"place_id": "0x287cf0225a1c0f9:0x78c06e25e68f9246", "name": "Ivision Systech Private Limited", "category": "Design engineer", "street": "412", "city": "E.W.S., Mukherjee Nagar, Raja Ram Nagar", "phone": "08269897542", "website": "https://www.ivisionsystech.com/", "rating": 5, "review_count": "", "latitude": 22.9665379, "longitude": 76.0391159, "maps_url": "https://www.google.com/maps/place/?q=place_id:0x287cf0225a1c0f9:0x78c06e25e68f9246"}, {"place_id": "0x396317001c296b89:0x77e424e0e3ff58b2", "name": "CodeMines Infotech", "category": "Software company", "street": "145/A", "city": "Kalani Bagh, Gomti Nagar", "phone": "", "website": "https://codeminesinfotech.com/", "rating": "", "review_count": "", "latitude": 22.9580417, "longitude": 76.043036, "maps_url": "https://www.google.com/maps/place/?q=place_id:0x396317001c296b89:0x77e424e0e3ff58b2"}, {"place_id": "0x390ce458d0000001:0xf2123bd299ec4501", "name": "IT Company India", "category": "Software company", "street": "D56", "city": "D Block, Sector 10", "phone": "09999244854", "website": "https://www.itcompanyindia.in/", "rating": 4.7, "review_count": "", "latitude": 28.589917699999997, "longitude": 77.3351153, "maps_url": "https://www.google.com/maps/place/?q=place_id:0x390ce458d0000001:0xf2123bd299ec4501"}, {"place_id": "0x3963178105555555:0xd9fef8466a74dc00", "name": "Alp Computer Education Institute", "category": "Computer service", "street": "133 LIG", "city": "Jawahar Nagar, Gomti Nagar", "phone": "", "website": "", "rating": 4.8, "review_count": "", "latitude": 22.953666, "longitude": 76.0416161, "maps_url": "https://www.google.com/maps/place/?q=place_id:0x3963178105555555:0xd9fef8466a74dc00"}, {"place_id": "0x396317edfc385939:0x496298098c0e8ec2", "name": "TOC LAPTOP SALES & SERVICE", "category": "Computer store", "street": "AB Rd", "city": "Kalani Bagh, Gomti Nagar", "phone": "09244288649", "website": "", "rating": 4.8, "review_count": "", "latitude": 22.9590136, "longitude": 76.0441106, "maps_url": "https://www.google.com/maps/place/?q=place_id:0x396317edfc385939:0x496298098c0e8ec2"}, {"place_id": "0x39631d5891adfb65:0xea28a34c2ba3a5ab", "name": "MoreYeahs", "category": "Software company", "street": "4th Floor", "city": "B ZONE BUSINESS SPACES", "phone": "09329911531", "website": "https://www.moreyeahs.com/", "rating": 4.3, "review_count": "", "latitude": 22.7708004, "longitude": 75.9103715, "maps_url": "https://www.google.com/maps/place/?q=place_id:0x39631d5891adfb65:0xea28a34c2ba3a5ab"}, {"place_id": "0x396319c47fa0d885:0x3cad63e7362f4bd4", "name": "Cummins Turbo Technologies pvt limited", "category": "Manufacturer", "street": "IDI-CTT Dewas indirect,AB Rd 455001", "city": "Industrial Area No.2", "phone": "", "website": "https://www.cummins.com/components/turbochargers", "rating": 4.4, "review_count": "", "latitude": 22.9332459, "longitude": 76.0218867, "maps_url": "https://www.google.com/maps/place/?q=place_id:0x396319c47fa0d885:0x3cad63e7362f4bd4"}, {"place_id": "0x3963170002e423fd:0x2845c60d9661c0f7", "name": "Adiyogi Enterprises", "category": "Computer service", "street": "Maina Shree Complex", "city": "AB Rd", "phone": "09926677787", "website": "", "rating": 5, "review_count": "", "latitude": 22.9637322, "longitude": 76.0473047, "maps_url": "https://www.google.com/maps/place/?q=place_id:0x3963170002e423fd:0x2845c60d9661c0f7"}, {"place_id": "0x396319e550167c0f:0xc21ae8f7a537ddd9", "name": "Win Infotech Software Solutions", "category": "Financial consultant", "street": "14", "city": "Labour Colony, Balaji Nagar", "phone": "09179298291", "website": "https://wininfotech.in/", "rating": 5, "review_count": "", "latitude": 22.947784, "longitude": 76.050197, "maps_url": "https://www.google.com/maps/place/?q=place_id:0x396319e550167c0f:0xc21ae8f7a537ddd9"}, {"place_id": "0x3963194c0a91d77d:0xc0227c345ba30719", "name": "Gabriel India Limited", "category": "Corporate office", "street": "Industrial Area No.2", "city": "Dewas, Madhya Pradesh 455001", "phone": "", "website": "", "rating": 4.1, "review_count": "", "latitude": 22.929257399999997, "longitude": 76.0389397, "maps_url": "https://www.google.com/maps/place/?q=place_id:0x3963194c0a91d77d:0xc0227c345ba30719"}, {"place_id": "0x3962fd3f35699959:0x60a1ecf32851850a", "name": "Chapter247 Infotech", "category": "Software company", "street": "6th Floor", "city": "611-612-613", "phone": "07773077715", "website": "https://www.chapter247.com/", "rating": 3.8, "review_count": "", "latitude": 22.7592613, "longitude": 75.9238235, "maps_url": "https://www.google.com/maps/place/?q=place_id:0x3962fd3f35699959:0x60a1ecf32851850a"}, {"place_id": "0x3962fd5594a5981f:0xe44d7df8e141cec9", "name": "Genesis Technologies", "category": "Software company", "street": "EB-103 Scheme Number 94, Ring Road", "city": "Service Rd", "phone": "", "website": "http://genesistechnologies.in/", "rating": 3.8, "review_count": "", "latitude": 22.760212499999998, "longitude": 75.90659409999999, "maps_url": "https://www.google.com/maps/place/?q=place_id:0x3962fd5594a5981f:0xe44d7df8e141cec9"}, {"place_id": "0x39633cc859d66b57:0xa5314ac94ec16e0a", "name": "Mita India Pvt Ltd Dewas", "category": "Auto parts manufacturer", "street": "X592+MX5", "city": "Khatamba, Madhya Pradesh 455115", "phone": "09868656580", "website": "http://imo.im/", "rating": 4, "review_count": "", "latitude": 22.969127, "longitude": 76.152496, "maps_url": "https://www.google.com/maps/place/?q=place_id:0x39633cc859d66b57:0xa5314ac94ec16e0a"}, {"place_id": "0x396319c8c2d58ded:0xfc9bf8b2d14e3cda", "name": "Surlon Precision Solutions India Limited", "category": "Manufacturer", "street": "Industrial Area No.2", "city": "Dewas, Madhya Pradesh 455001", "phone": "07272258373", "website": "http://www.tataprecision.com/", "rating": 4.4, "review_count": "", "latitude": 22.933703599999998, "longitude": 76.021577, "maps_url": "https://www.google.com/maps/place/?q=place_id:0x396319c8c2d58ded:0xfc9bf8b2d14e3cda"}, {"place_id": "0x3963182895e1496d:0xede05683e44b2437", "name": "The Bit Computers", "category": "Computer store", "street": "29, Balgarh Rd", "city": "Balaji Nagar", "phone": "08103469288", "website": "", "rating": 4.4, "review_count": "", "latitude": 22.9494713, "longitude": 76.0514321, "maps_url": "https://www.google.com/maps/place/?q=place_id:0x3963182895e1496d:0xede05683e44b2437"}, {"place_id": "0x396317bd43c6cae9:0x93e7d2a1d33dd13f", "name": "Anahcra Infotech Private Limited", "category": "Marketing agency", "street": "81, Khari Bawadi Road", "city": "Old Town, Hanuman Bakhal", "phone": "07987071323", "website": "", "rating": 5, "review_count": "", "latitude": 22.9622605, "longitude": 76.0569897, "maps_url": "https://www.google.com/maps/place/?q=place_id:0x396317bd43c6cae9:0x93e7d2a1d33dd13f"}, {"place_id": "0x396319e7b24e0b9d:0x3e56ec0df631cef1", "name": "Vippy Industries Limited", "category": "Food Processing Company", "street": "28, AB Rd", "city": "Industrial Area No. 1", "phone": "07272258545", "website": "http://www.vippysoya.com/", "rating": 3.8, "review_count": "", "latitude": 22.9384363, "longitude": 76.0143614, "maps_url": "https://www.google.com/maps/place/?q=place_id:0x396319e7b24e0b9d:0x3e56ec0df631cef1"}, {"place_id": "0x396317d7b9fce5ed:0x76f34aad91692f9e", "name": "Cyber Veins", "category": "Software company", "street": "", "city": "", "phone": "08085747661", "website": "http://cyber-veins.in/", "rating": 5, "review_count": "", "latitude": 14.157641199999999, "longitude": -16.7424939, "maps_url": "https://www.google.com/maps/place/?q=place_id:0x396317d7b9fce5ed:0x76f34aad91692f9e"}, {"place_id": "0x396323d083de3151:0x9c2e0f26db50caf5", "name": "Jan Sewa Kendr", "category": "Computer support and services", "street": "Shop No. 2 Megic Stend Kankund Kankund", "city": "Dewas, Madhya Pradesh 455001", "phone": "09770804882", "website": "", "rating": 4.8, "review_count": "", "latitude": 22.9405847, "longitude": 76.1500439, "maps_url": "https://www.google.com/maps/place/?q=place_id:0x396323d083de3151:0x9c2e0f26db50caf5"}, {"place_id": "0x39631938dd401e93:0xf2699c0bfbb1ada1", "name": "Linamar India Private Limited (Dewas)", "category": "Auto parts manufacturer", "street": "Police Colony, Industrial Area No. 3", "city": "Dewas, Madhya Pradesh 455001", "phone": "", "website": "http://www.linamar.com/", "rating": 4.3, "review_count": "", "latitude": 22.9333843, "longitude": 76.0362854, "maps_url": "https://www.google.com/maps/place/?q=place_id:0x39631938dd401e93:0xf2699c0bfbb1ada1"}, {"place_id": "0x3963178ffffffffd:0xcb341924a729e52", "name": "Giraffe Storage Solution", "category": "Manufacturer", "street": "B,C, D1&9E Industrial Area", "city": "10", "phone": "09993590431", "website": "https://www.giraffestorage.com/", "rating": 4.7, "review_count": "", "latitude": 22.9647808, "longitude": 76.04814449999999, "maps_url": "https://www.google.com/maps/place/?q=place_id:0x3963178ffffffffd:0xcb341924a729e52"}, {"place_id": "0x3963173647bb8e3d:0x61da9f1d94156c82", "name": "Dmgenix \u2014 Registered Startup India", "category": "Software company", "street": "Office Add 183", "city": "Alkapuri Rd", "phone": "08959498718", "website": "https://dmgenix.com/", "rating": 5, "review_count": "", "latitude": 22.9685728, "longitude": 76.03925269999999, "maps_url": "https://www.google.com/maps/place/?q=place_id:0x3963173647bb8e3d:0x61da9f1d94156c82"}, {"place_id": "0x396319e845555555:0x1b3842080da83c8a", "name": "Dewas Metal Sections Ltd.", "category": "Manufacturer", "street": "W2C5+HGF", "city": "AB Rd", "phone": "08435501485", "website": "https://www.dmsl.co.in/", "rating": 4.4, "review_count": "", "latitude": 22.9224118, "longitude": 76.0073221, "maps_url": "https://www.google.com/maps/place/?q=place_id:0x396319e845555555:0x1b3842080da83c8a"}, {"place_id": "0x396317429c9bf8df:0x89fa0b04aa6f15c3", "name": "Times Of Computer Dewas ( TOC )", "category": "Computer service", "street": "11, AB Rd", "city": "above Airtel office", "phone": "07828809300", "website": "https://www.timesofcomputer.com/", "rating": 4.8, "review_count": "", "latitude": 22.960112499999997, "longitude": 76.0437486, "maps_url": "https://www.google.com/maps/place/?q=place_id:0x396317429c9bf8df:0x89fa0b04aa6f15c3"}, {"place_id": "0x39631708d5d6fd53:0x6cf93c0e550356c9", "name": "Sharda Associates Engineers and Architect", "category": "Corporate office", "street": "MR-3", "city": "67 Balaji Dham, Balgarh Rd", "phone": "09584292171", "website": "", "rating": 4.9, "review_count": "", "latitude": 22.9471267, "longitude": 76.0373015, "maps_url": "https://www.google.com/maps/place/?q=place_id:0x39631708d5d6fd53:0x6cf93c0e550356c9"}, {"place_id": "0x39633d3037096f77:0xc2faa50a9a4ce05", "name": "John Deere Dewas Works", "category": "Manufacturer", "street": "Indore - Bhopal Rd", "city": "Khatamba, Madhya Pradesh 455001", "phone": "18002095310", "website": "http://www.deere.co.in/", "rating": 4.5, "review_count": "", "latitude": 22.966046799999997, "longitude": 76.1191446, "maps_url": "https://www.google.com/maps/place/?q=place_id:0x39633d3037096f77:0xc2faa50a9a4ce05"}, {"place_id": "0x39632377885c3f4f:0x6832297a18ca0177", "name": "Mahakal Mp Online", "category": "Computer support and services", "street": "Rajoda", "city": "Dubul Choki Road", "phone": "08349975739", "website": "", "rating": 5, "review_count": "", "latitude": 22.945839, "longitude": 76.0939291, "maps_url": "https://www.google.com/maps/place/?q=place_id:0x39632377885c3f4f:0x6832297a18ca0177"}, {"place_id": "0x3be7c21b5901e181:0x7fe794585addc1f6", "name": "Smartinfologiks - Software Development Company in India | IT Solutions", "category": "Software company", "street": "Hilton Center", "city": "514", "phone": "07400064691", "website": "https://www.smartinfologiks.com/", "rating": 4.6, "review_count": "", "latitude": 19.0139592, "longitude": 73.0382705, "maps_url": "https://www.google.com/maps/place/?q=place_id:0x3be7c21b5901e181:0x7fe794585addc1f6"}, {"place_id": "0x39631782a9679ba9:0xf1599ba222c300e5", "name": "Keval Kevara Business Consultant", "category": "Business management consultant", "street": "81-82", "city": "Seth Miksilal Nagar, Mishrilal Nagar, Square", "phone": "09589034537", "website": "https://www.badabusiness.com/digitaldukan/BIKK009122", "rating": 5, "review_count": "", "latitude": 22.9549733, "longitude": 76.0390682, "maps_url": "https://www.google.com/maps/place/?q=place_id:0x39631782a9679ba9:0xf1599ba222c300e5"}, {"place_id": "0x396302aaf5500001:0xb7ca9e747df71628", "name": "Codingkart IT Services", "category": "Software company", "street": "", "city": "", "phone": "08349889628", "website": "http://www.codingkart.com/", "rating": 4.1, "review_count": "", "latitude": 21.0680074, "longitude": 82.7525294, "maps_url": "https://www.google.com/maps/place/?q=place_id:0x396302aaf5500001:0xb7ca9e747df71628"}, {"place_id": "0x3bc2becdc35b6937:0x515ac559c349eee3", "name": "Thinkitive Technologies Private Limited", "category": "Software company", "street": "4th Floor", "city": "ABIL IMPERIAL COMMERCIAL SPACES", "phone": "08956467327", "website": "https://www.thinkitive.com/", "rating": 3.9, "review_count": "", "latitude": 18.5563888, "longitude": 73.7729748, "maps_url": "https://www.google.com/maps/place/?q=place_id:0x3bc2becdc35b6937:0x515ac559c349eee3"}, {"place_id": "0x396317dc64b8bb69:0xfd672c4f5a8eba2a", "name": "Wardhan Training & Placement Company", "category": "Education center", "street": "Kela Devi", "city": "Chauraha, AB Rd", "phone": "07400746609", "website": "https://wardhantraining.com/", "rating": 5, "review_count": "", "latitude": 22.9546028, "longitude": 76.0388238, "maps_url": "https://www.google.com/maps/place/?q=place_id:0x396317dc64b8bb69:0xfd672c4f5a8eba2a"}, {"place_id": "0x396317b791f9f921:0xaa9d68312ca2f97b", "name": "Robopie Inc.", "category": "Research and product development", "street": "48/A", "city": "near The Guardian School", "phone": "09479561907", "website": "https://www.robopie.in/", "rating": "", "review_count": "", "latitude": 22.9586862, "longitude": 76.0394522, "maps_url": "https://www.google.com/maps/place/?q=place_id:0x396317b791f9f921:0xaa9d68312ca2f97b"}, {"place_id": "0x3963197594e37b01:0x3c6305bf1d6ba4bf", "name": "DCI~Consortium Group", "category": "Marketing agency", "street": "DCI Consortium Group", "city": "near Mill", "phone": "09174131383", "website": "", "rating": 5, "review_count": "", "latitude": 22.9430001, "longitude": 76.0538978, "maps_url": "https://www.google.com/maps/place/?q=place_id:0x3963197594e37b01:0x3c6305bf1d6ba4bf"}, {"place_id": "0x39631783ab28463d:0x47360e8151298220", "name": "Malwas Axiom Build Tech pvt. Ltd.", "category": "Architect", "street": "malwa shenai Complex", "city": "630/13, AB Rd", "phone": "09179999337", "website": "", "rating": 4.8, "review_count": "", "latitude": 22.9581523, "longitude": 76.04200569999999, "maps_url": "https://www.google.com/maps/place/?q=place_id:0x39631783ab28463d:0x47360e8151298220"}, {"place_id": "0x3963174fac2852f7:0xb45d22ceacd982fc", "name": "Post Production Work", "category": "Video editing service", "street": "18", "city": "near Dominos", "phone": "07974063067", "website": "https://gigxomi.com/", "rating": 5, "review_count": "", "latitude": 22.9629005, "longitude": 76.0458629, "maps_url": "https://www.google.com/maps/place/?q=place_id:0x3963174fac2852f7:0xb45d22ceacd982fc"}, {"place_id": "0x3962578f392034bb:0xce07ed72e2db8009", "name": "Endo India Par Formulations Private Limited", "category": "Pharmaceutical company", "street": "W2JH+CM4", "city": "Indore-SEZ", "phone": "", "website": "https://www.parpharm.com/", "rating": 4.7, "review_count": "", "latitude": 22.931010699999998, "longitude": 76.029202, "maps_url": "https://www.google.com/maps/place/?q=place_id:0x3962578f392034bb:0xce07ed72e2db8009"}, {"place_id": "0x3963172e8a8361c5:0xd183a76387b929aa", "name": "Urbanizer Clothing Co.", "category": "Manufacturer", "street": "Suncity 1", "city": "183, AB Rd", "phone": "09755688860", "website": "https://www.urbanizer.in/", "rating": 5, "review_count": "", "latitude": 22.9471591, "longitude": 76.0294474, "maps_url": "https://www.google.com/maps/place/?q=place_id:0x3963172e8a8361c5:0xd183a76387b929aa"}, {"place_id": "0x396319a429a38e4d:0xce36150924984b42", "name": "Aameya Polymers LLP", "category": "Manufacturer", "street": "Survey No. 137/2, P/H. No. 57, Gram Anbatpura", "city": "Dewas, Madhya Pradesh 455001", "phone": "09424422372", "website": "", "rating": 4.5, "review_count": "", "latitude": 22.920410999999998, "longitude": 76.0264408, "maps_url": "https://www.google.com/maps/place/?q=place_id:0x396319a429a38e4d:0xce36150924984b42"}, {"place_id": "0x396319cdae4f6045:0x2704a018fad24983", "name": "Devendra Techno Industries \u2122", "category": "Manufacturer", "street": "No. 117- B", "city": "Industrial Area No.2", "phone": "09827020698", "website": "https://www.dtimachines.com/", "rating": 3.7, "review_count": "", "latitude": 22.9351828, "longitude": 76.0356839, "maps_url": "https://www.google.com/maps/place/?q=place_id:0x396319cdae4f6045:0x2704a018fad24983"}, {"place_id": "0x3963179b198afb39:0x746bcc2c170e99cd", "name": "Docxhub", "category": "Software company", "street": "5-A Kothi Road", "city": "opposite to khedapati International hotel", "phone": "08269034006", "website": "https://docxhub.in/", "rating": 4, "review_count": "", "latitude": 22.9655179, "longitude": 76.04609479999999, "maps_url": "https://www.google.com/maps/place/?q=place_id:0x3963179b198afb39:0x746bcc2c170e99cd"}, {"place_id": "0x3963172bd349136d:0x1b734e3eb8f2ff47", "name": "Horizon Solar", "category": "Solar Energy Company", "street": "143", "city": "Ram Nagar Extension, Tilak Nagar, Ram Nagar", "phone": "07387378997", "website": "", "rating": 5, "review_count": "", "latitude": 22.9588827, "longitude": 76.04140269999999, "maps_url": "https://www.google.com/maps/place/?q=place_id:0x3963172bd349136d:0x1b734e3eb8f2ff47"}, {"place_id": "0x3963174fac2852f7:0xb45d22ceacd982fc", "name": "Post Production Work", "category": "Video editing service", "street": "18", "city": "near Dominos", "phone": "07974063067", "website": "https://gigxomi.com/", "rating": 5, "review_count": "", "latitude": 22.9629005, "longitude": 76.0458629, "maps_url": "https://www.google.com/maps/place/?q=place_id:0x3963174fac2852f7:0xb45d22ceacd982fc"}, {"place_id": "0x39631dbb2049dd65:0xb667eb306f1b92c5", "name": "IT Company", "category": "Information services", "street": "Chikitsak Nagar", "city": "Indore, Madhya Pradesh 452010", "phone": "", "website": "", "rating": 2, "review_count": "", "latitude": 22.7569083, "longitude": 75.9056753, "maps_url": "https://www.google.com/maps/place/?q=place_id:0x39631dbb2049dd65:0xb667eb306f1b92c5"}, {"place_id": "0x39631d6ae4f42a97:0x83bc825e66f9983", "name": "Techwave IT Solutions Pvt Ltd | Software Development Company in Indore | Top IT Company in Indore | India", "category": "Software company", "street": "Bhopal Motors JCB", "city": "near Panchvati", "phone": "09009155444", "website": "http://techwaveitsolutions.com/", "rating": "", "review_count": "", "latitude": 22.792078399999998, "longitude": 75.90735409999999, "maps_url": "https://www.google.com/maps/place/?q=place_id:0x39631d6ae4f42a97:0x83bc825e66f9983"}, {"place_id": "0x6b406bef7cd437b1:0x28334f0b498e4068", "name": "Triangle Solar Energy Dewas", "category": "Solar Energy Company", "street": "41B", "city": "Vikas Nagar, Ramchandra Nagar, Gomti Nagar", "phone": "09977667330", "website": "https://sites.google.com/view/triangleenterprises/home", "rating": 4.8, "review_count": "", "latitude": 22.9479908, "longitude": 76.038437, "maps_url": "https://www.google.com/maps/place/?q=place_id:0x6b406bef7cd437b1:0x28334f0b498e4068"}, {"place_id": "0x39631781e29c00b5:0x4ed412390ad4fa4d", "name": "TRIHDI MANAGEMENT AND OUTSOURCING SOLUTIONS PVT LTD", "category": "Human resource consulting", "street": "First floor 03, Opt. Ksheer Sagar Dairy, SK Tower", "city": "Plot 106,04, First floor", "phone": "08889698674", "website": "https://www.trihdiconsulting.com/", "rating": 2.7, "review_count": "", "latitude": 22.955031899999998, "longitude": 76.0381707, "maps_url": "https://www.google.com/maps/place/?q=place_id:0x39631781e29c00b5:0x4ed412390ad4fa4d"}, {"place_id": "0x3963197594e37b01:0x3c6305bf1d6ba4bf", "name": "DCI~Consortium Group", "category": "Marketing agency", "street": "DCI Consortium Group", "city": "near Mill", "phone": "09174131383", "website": "", "rating": 5, "review_count": "", "latitude": 22.9430001, "longitude": 76.0538978, "maps_url": "https://www.google.com/maps/place/?q=place_id:0x3963197594e37b01:0x3c6305bf1d6ba4bf"}, {"place_id": "0x39631834933c0a2d:0x5e6c39bcf3857f7e", "name": "VE Commercial", "category": "Manufacturer", "street": "Police Colony, Industrial Area No. 3", "city": "Dewas, Madhya Pradesh 455001", "phone": "", "website": "http://www.vecv.in/", "rating": 4, "review_count": "", "latitude": 22.931657299999998, "longitude": 76.04093639999999, "maps_url": "https://www.google.com/maps/place/?q=place_id:0x39631834933c0a2d:0x5e6c39bcf3857f7e"}, {"place_id": "0x396319dd15118047:0x3ebaca68feb4ac70", "name": "Tata International Limited", "category": "Manufacturer", "street": "AB Rd", "city": "Industrial Area No. 1", "phone": "", "website": "http://www.tatainternational.com/", "rating": 4.5, "review_count": "", "latitude": 22.9374239, "longitude": 76.0174308, "maps_url": "https://www.google.com/maps/place/?q=place_id:0x396319dd15118047:0x3ebaca68feb4ac70"}, {"place_id": "0x396319cd9c0c7cd5:0xa544a4064dc1a99f", "name": "H & R Johnson Ltd.", "category": "Ceramic manufacturer", "street": "InFront of Malwa Strips", "city": "Industrial Area", "phone": "1800227484", "website": "http://www.hrjohnsonindia.com/", "rating": 4.2, "review_count": "", "latitude": 22.936693899999998, "longitude": 76.0319124, "maps_url": "https://www.google.com/maps/place/?q=place_id:0x396319cd9c0c7cd5:0xa544a4064dc1a99f"}, {"place_id": "0x39631783d4998dd5:0xc5d2ecd6ee4add19", "name": "LG Best Shop-ROYAL ELECTRONICS IND", "category": "Electronics Company", "street": "ROYAL ELECTRONICS IND 8", "city": "AB Rd", "phone": "", "website": "https://www.lg.com/in?utm_source=google&utm_medium=gmb", "rating": 4.6, "review_count": "", "latitude": 22.9597461, "longitude": 76.0433954, "maps_url": "https://www.google.com/maps/place/?q=place_id:0x39631783d4998dd5:0xc5d2ecd6ee4add19"}, {"place_id": "0x396317f7dfd73b93:0x8da54c23289a9544", "name": "Sunpower", "category": "Solar Energy Company", "street": "60 ews", "city": "New Mukherjee Nagar, Anukul Nagar", "phone": "", "website": "", "rating": 5, "review_count": "", "latitude": 22.9703311, "longitude": 76.037122, "maps_url": "https://www.google.com/maps/place/?q=place_id:0x396317f7dfd73b93:0x8da54c23289a9544"}, {"place_id": "0x396317904a94f707:0xc1d2b7473f420122", "name": "Ravi Electricals solar solutions", "category": "Solar Energy Company", "street": "Infront of rajmal pannalal shop", "city": "55, MG Rd", "phone": "09425047580", "website": "http://www.ravisolarenergy.in/", "rating": 4.7, "review_count": "", "latitude": 22.964137899999997, "longitude": 76.05348459999999, "maps_url": "https://www.google.com/maps/place/?q=place_id:0x396317904a94f707:0xc1d2b7473f420122"}, {"place_id": "0x39631933b1def0dd:0xe962e366c5ab07b4", "name": "Sai Chhaya", "category": "Housing society", "street": "Dewas, Madhya Pradesh 455001", "city": "", "phone": "", "website": "", "rating": 4.9, "review_count": "", "latitude": 22.940187899999998, "longitude": 76.06061609999999, "maps_url": "https://www.google.com/maps/place/?q=place_id:0x39631933b1def0dd:0xe962e366c5ab07b4"}, {"place_id": "0x396319f659dad8f9:0xfebf479257a5399d", "name": "Eicher Dewas", "category": "Corporate office", "street": "W2JR+HFP", "city": "Vikas Nagar, Police Colony, Industrial Area No. 3", "phone": "", "website": "", "rating": 4, "review_count": "", "latitude": 22.9314617, "longitude": 76.041195, "maps_url": "https://www.google.com/maps/place/?q=place_id:0x396319f659dad8f9:0xfebf479257a5399d"}, {"place_id": "0x396319cb37e8f4e1:0x2871ab253cebb422", "name": "Dewas Hydroquip Pvt. Ltd.", "category": "Hose supplier", "street": "65, Industrial Area No. 3, A. B. Road", "city": "Dewas, Madhya Pradesh 455001", "phone": "07272258868", "website": "http://www.dewashydroquip.com/", "rating": 3.4, "review_count": "", "latitude": 22.931954899999997, "longitude": 76.0391159, "maps_url": "https://www.google.com/maps/place/?q=place_id:0x396319cb37e8f4e1:0x2871ab253cebb422"}, {"place_id": "0x396317167a9035bb:0x253ed9b47e3f4ccf", "name": "Garnet Tools", "category": "Factory equipment supplier", "street": "2-D, Industrial Area", "city": "Ujjain Rd", "phone": "09827333191", "website": "http://www.garnetindia.com/", "rating": 4.4, "review_count": "", "latitude": 22.9745955, "longitude": 76.0464949, "maps_url": "https://www.google.com/maps/place/?q=place_id:0x396317167a9035bb:0x253ed9b47e3f4ccf"}, {"place_id": "0x396323f2b8467dd7:0x8c995159bf3f371b", "name": "JMD Online& Studio", "category": "Computer support and services", "street": "Laxmi Nagar", "city": "Napakhedi, Madhya Pradesh 455001", "phone": "", "website": "", "rating": "", "review_count": "", "latitude": 22.9043661, "longitude": 76.1493558, "maps_url": "https://www.google.com/maps/place/?q=place_id:0x396323f2b8467dd7:0x8c995159bf3f371b"}, {"place_id": "0x396317695d85cee1:0xa7a483c95ed13bab", "name": "ResearchVia", "category": "Finance broker", "street": "129 A", "city": "Kalani Bagh, Gomti Nagar", "phone": "07805066366", "website": "https://researchvia.in/", "rating": 4, "review_count": "", "latitude": 22.958214599999998, "longitude": 76.0429343, "maps_url": "https://www.google.com/maps/place/?q=place_id:0x396317695d85cee1:0xa7a483c95ed13bab"}, {"place_id": "0x396319dc55555555:0xe3b4ca4c2bf555", "name": "Maya Fan Air Engineering Pvt Ltd", "category": "Manufacturer", "street": "Plot No: 53-B, Industrial Area No: 1, A. B. Road", "city": "Dewas, Madhya Pradesh 455001", "phone": "09425047574", "website": "https://www.mayafans.com/", "rating": 4.8, "review_count": "", "latitude": 22.9499046, "longitude": 76.0239909, "maps_url": "https://www.google.com/maps/place/?q=place_id:0x396319dc55555555:0xe3b4ca4c2bf555"}, {"place_id": "0x3963179a02c00e9d:0x654586692fd7e595", "name": "Taj Food's", "category": "Food Processing Company", "street": "Laxmi park", "city": "Shivaji Nagar, Moti Bunglow", "phone": "09893100770", "website": "", "rating": 4.9, "review_count": "", "latitude": 22.9685819, "longitude": 76.0503107, "maps_url": "https://www.google.com/maps/place/?q=place_id:0x3963179a02c00e9d:0x654586692fd7e595"}, {"place_id": "0x396317850c0d551f:0x24d7df04573d1d00", "name": "Bharat Sanchar Nigam Limited Office", "category": "Telecommunications service provider", "street": "X25X+RJW", "city": "Bhagat Singh Marg", "phone": "18003451500", "website": "http://www.bsnl.co.in/", "rating": 3.7, "review_count": "", "latitude": 22.9596075, "longitude": 76.0490721, "maps_url": "https://www.google.com/maps/place/?q=place_id:0x396317850c0d551f:0x24d7df04573d1d00"}, {"place_id": "0x396323d224547c0d:0x8158c604accb85f6", "name": "Kalyx Warehousing CM", "category": "Warehouse", "street": "Gayatri Warehouse", "city": "Siroliya, Madhya Pradesh 455001", "phone": "07961706000", "website": "https://kalyxwarehousing.com/", "rating": 3.1, "review_count": "", "latitude": 22.876019, "longitude": 76.1378612, "maps_url": "https://www.google.com/maps/place/?q=place_id:0x396323d224547c0d:0x8158c604accb85f6"}, {"place_id": "0x390ce55ffe34c78d:0x5e0691a2f679aa6a", "name": "ANR Software Private Limited", "category": "Software company", "street": "B 103-104, Sector 63 Rd", "city": "B Block, Sector 63", "phone": "", "website": "https://www.anrsoftware.com/", "rating": 3.9, "review_count": "", "latitude": 28.615819, "longitude": 77.3785242, "maps_url": "https://www.google.com/maps/place/?q=place_id:0x390ce55ffe34c78d:0x5e0691a2f679aa6a"}, {"place_id": "0x396317470804287d:0xef40f4990ba60f15", "name": "Budget Repair & Service", "category": "Air conditioning repair service", "street": "Shop no. 1, 174", "city": "Silvar Park Colony", "phone": "08889993015", "website": "https://budget-repair-service.grexa.site/", "rating": 4.8, "review_count": "", "latitude": 22.9474631, "longitude": 76.0559547, "maps_url": "https://www.google.com/maps/place/?q=place_id:0x396317470804287d:0xef40f4990ba60f15"}, {"place_id": "0x3963175dbfbef98b:0x5ddd1ccdfba37de0", "name": "Trushja Softech", "category": "Software company", "street": "in front of Sharda Mata Mandir", "city": "Chamunda Kunj Colony, Mishrilal Nagar, Ganga Nagar", "phone": "07771094445", "website": "http://trushjasoftech.in/", "rating": "", "review_count": "", "latitude": 22.9539071, "longitude": 76.0376828, "maps_url": "https://www.google.com/maps/place/?q=place_id:0x3963175dbfbef98b:0x5ddd1ccdfba37de0"}, {"place_id": "0x6a8791b17a2ad1f3:0x3320f692d9651905", "name": "Pixxel fx", "category": "Software company", "street": "", "city": "", "phone": "", "website": "http://pixxelfx.com/", "rating": "", "review_count": "", "latitude": 22.0240832, "longitude": 153.1842336, "maps_url": "https://www.google.com/maps/place/?q=place_id:0x6a8791b17a2ad1f3:0x3320f692d9651905"}, {"place_id": "0x39631954dd28d29d:0x8d4efa3370bdba60", "name": "Divyanshi Online Service", "category": "Computer support and services", "street": "312, Ganesh Mandir Road", "city": "Khati Chowk", "phone": "06261169304", "website": "", "rating": "", "review_count": "", "latitude": 22.909687299999998, "longitude": 76.0473583, "maps_url": "https://www.google.com/maps/place/?q=place_id:0x39631954dd28d29d:0x8d4efa3370bdba60"}, {"place_id": "0x396317a49f3919dd:0x71cc474768e7fa4b", "name": "Kirloskar Brothers Limited", "category": "Manufacturer", "street": "X2HX+PHF", "city": "Station Rd", "phone": "07272227397", "website": "https://www.kirloskarpumps.com/", "rating": 4.1, "review_count": "", "latitude": 22.9793044, "longitude": 76.0489221, "maps_url": "https://www.google.com/maps/place/?q=place_id:0x396317a49f3919dd:0x71cc474768e7fa4b"}, {"place_id": "0x3963179a4a88bfc9:0xbcaa011b9e3b8f69", "name": "Codezesk Technologies", "category": "E - Commerce Agency", "street": "A-11", "city": "Forest colony, HO, Moti Bunglow", "phone": "", "website": "", "rating": "", "review_count": "", "latitude": 22.966345699999998, "longitude": 76.048048, "maps_url": "https://www.google.com/maps/place/?q=place_id:0x3963179a4a88bfc9:0xbcaa011b9e3b8f69"}, {"place_id": "0x3963178617e9f813:0x28416f9515be3caf", "name": "Service Chuno", "category": "Marketing agency", "street": "38/1", "city": "38/1", "phone": "06267605079", "website": "", "rating": 4.2, "review_count": "", "latitude": 22.9692358, "longitude": 76.0391796, "maps_url": "https://www.google.com/maps/place/?q=place_id:0x3963178617e9f813:0x28416f9515be3caf"}, {"place_id": "0x3963178c45180d57:0x12d4efa96fae4e31", "name": "My Digital Hub | Digital Marketing Agency Dewas", "category": "Internet marketing service", "street": "3rd floor", "city": "11, AB Rd", "phone": "07440461569", "website": "", "rating": 4, "review_count": "", "latitude": 22.9599199, "longitude": 76.0435969, "maps_url": "https://www.google.com/maps/place/?q=place_id:0x3963178c45180d57:0x12d4efa96fae4e31"}, {"place_id": "0x39631999985dace7:0x1edfe1e23870ce60", "name": "Vijay Laxmi Online Services", "category": "Computer support and services", "street": "55 Bairwachal Colony Near Bye Ramdev Mandir Ke Pass", "city": "Dewas, Madhya Pradesh 455001", "phone": "09893334437", "website": "", "rating": "", "review_count": "", "latitude": 22.9441292, "longitude": 76.0532553, "maps_url": "https://www.google.com/maps/place/?q=place_id:0x39631999985dace7:0x1edfe1e23870ce60"}, {"place_id": "0x396319687e19aab5:0x51cf5c17bf3bf3c0", "name": "SHREE JI MP ONLINE", "category": "Computer support and services", "street": "Sidhraj Nagar, Balgarh Rd", "city": "Gomti Nagar", "phone": "06266088721", "website": "", "rating": "", "review_count": "", "latitude": 22.944226, "longitude": 76.044777, "maps_url": "https://www.google.com/maps/place/?q=place_id:0x396319687e19aab5:0x51cf5c17bf3bf3c0"}, {"place_id": "0x396319687e19aab5:0x51cf5c17bf3bf3c0", "name": "SHREE JI MP ONLINE", "category": "Computer support and services", "street": "Sidhraj Nagar, Balgarh Rd", "city": "Gomti Nagar", "phone": "06266088721", "website": "", "rating": "", "review_count": "", "latitude": 22.944226, "longitude": 76.044777, "maps_url": "https://www.google.com/maps/place/?q=place_id:0x396319687e19aab5:0x51cf5c17bf3bf3c0"}]}