{"timestamp": 1774416559.838702, "keyword": "school", "location": "bhilwara", "cell_idx": 164, "results": [{"place_id": "%E0%A4%B0%E0%A4%BE%E0%A4%9C%E0%A4%95%E0%A4%BF%E0%A4%AF+%E0%A4%AA%E0%A5%8D%E0%A4%B0%E0%A4%BE%E0%A4%A5%E0%A4%AE%E0%A4%BF%E0%A4%95+%E0%A4%B5%E0%A4%BF%E0%A4%A7%E0%A5%8D%E0%A4%AF%E0%A4%BE%E0%A4%B2%E0%A4%AF+%E0%A4%95%E0%A4%BE%E0%A4%AA%E0%A4%A1%E0%A4%BF%E0%A4%AF%E0%A4%BE", "name": "\u0930\u093e\u091c\u0915\u093f\u092f \u092a\u094d\u0930\u093e\u0925\u092e\u093f\u0915 \u0935\u093f\u0927\u094d\u092f\u093e\u0932\u092f \u0915\u093e\u092a\u0921\u093f\u092f\u093e", "category": "No reviews", "street": "Primary school \u00b7 \ue934 \u00b7 98PR+RFCOpen 24 hours", "phone": "", "website": "", "rating": "", "review_count": "", "maps_url": "https://www.google.com/maps/place/%E0%A4%B0%E0%A4%BE%E0%A4%9C%E0%A4%95%E0%A4%BF%E0%A4%AF+%E0%A4%AA%E0%A5%8D%E0%A4%B0%E0%A4%BE%E0%A4%A5%E0%A4%AE%E0%A4%BF%E0%A4%95+%E0%A4%B5%E0%A4%BF%E0%A4%A7%E0%A5%8D%E0%A4%AF%E0%A4%BE%E0%A4%B2%E0%A4%AF+%E0%A4%95%E0%A4%BE%E0%A4%AA%E0%A4%A1%E0%A4%BF%E0%A4%AF%E0%A4%BE/data=!4m7!3m6!1s0x3968fb386f6a495f:0x7879d661390278e6!8m2!3d25.3870508!4d74.3411515!16s%2Fg%2F11j2y7p98j!19sChIJX0lqbzj7aDkR5ngCOWHWeXg?authuser=0&hl=en&rclk=1", "latitude": 25.3870508, "longitude": 74.3411515}, {"place_id": "Govt.+Upper+Primary+School+Kapadiya", "name": "Govt. Upper Primary School Kapadiya", "category": "No reviews", "street": "Elementary school \u00b7 \ue934 \u00b7 98PJ+RJV", "phone": "", "website": "", "rating": "", "review_count": "", "maps_url": "https://www.google.com/maps/place/Govt.+Upper+Primary+School+Kapadiya/data=!4m7!3m6!1s0x3968fb72e19b4fbb:0x1395cffc12fc842e!8m2!3d25.3871081!4d74.3315374!16s%2Fg%2F11nxd10h_9!19sChIJu0-b4XL7aDkRLoT8EvzPlRM?authuser=0&hl=en&rclk=1", "latitude": 25.3871081, "longitude": 74.3315374}, {"place_id": "Govt.+Primary+school+kharoliya+khera", "name": "Govt. Primary school kharoliya khera", "category": "No reviews", "street": "Primary school \u00b7 \ue934 \u00b7 99X8+Q32, Road", "phone": "", "website": "", "rating": "", "review_count": "", "maps_url": "https://www.google.com/maps/place/Govt.+Primary+school+kharoliya+khera/data=!4m7!3m6!1s0x3968fbc2baab6319:0xbd6617a6b1b5dab5!8m2!3d25.3993961!4d74.3651382!16s%2Fg%2F11fhrjc7ps!19sChIJGWOrusL7aDkRtdq1saYXZr0?authuser=0&hl=en&rclk=1", "latitude": 25.3993961, "longitude": 74.3651382}, {"place_id": "Government+Primary+School+Mangalpura", "name": "Government Primary School Mangalpura", "category": "No reviews", "street": "Primary school \u00b7 \ue934 \u00b7 C887+WV7", "phone": "", "website": "", "rating": "", "review_count": "", "maps_url": "https://www.google.com/maps/place/Government+Primary+School+Mangalpura/data=!4m7!3m6!1s0x3968fb7462fce483:0x2560c9509e5e8418!8m2!3d25.4172782!4d74.3146801!16s%2Fg%2F11fkdmrm_m!19sChIJg-T8YnT7aDkRGIRenlDJYCU?authuser=0&hl=en&rclk=1", "latitude": 25.4172782, "longitude": 74.3146801}, {"place_id": "Govt.+girl%27s+upper+primary+school,+chandras", "name": "Govt. girl's upper primary school, chandras", "category": "No reviews", "street": "Elementary school \u00b7 \ue934 \u00b7 C8HF+G28Open \u00b7 Closes 4\u202fpm", "phone": "", "website": "", "rating": "", "review_count": "", "maps_url": "https://www.google.com/maps/place/Govt.+girl%27s+upper+primary+school,+chandras/data=!4m7!3m6!1s0x3968fbd0c4e45409:0x7cfa80372a491e5d!8m2!3d25.428819!4d74.322507!16s%2Fg%2F11pyj5slfw!19sChIJCVTkxND7aDkRXR5JKjeA-nw?authuser=0&hl=en&rclk=1", "latitude": 25.428819, "longitude": 74.322507}, {"place_id": "sr.Sec.+School+Chandras", "name": "sr.Sec. School Chandras", "category": "No reviews", "street": "Secondary school \u00b7 \ue934 \u00b7 C8GF+2F4", "phone": "", "website": "", "rating": "", "review_count": "", "maps_url": "https://www.google.com/maps/place/sr.Sec.+School+Chandras/data=!4m7!3m6!1s0x3968fa32a9b1dbf5:0x81647f86fd72b68f!8m2!3d25.4250228!4d74.3236896!16s%2Fg%2F11hbl71ypb!19sChIJ9duxqTL6aDkRj7Zy_YZ_ZIE?authuser=0&hl=en&rclk=1", "latitude": 25.4250228, "longitude": 74.3236896}, {"place_id": "%E0%A4%B0%E0%A4%BE%E0%A4%9C%E0%A4%95%E0%A4%BF%E0%A4%AF+%E0%A4%AE%E0%A4%BE%E0%A4%A7%E0%A5%8D%E0%A4%AF%E0%A4%AE%E0%A4%BF%E0%A4%95+%E0%A4%B5%E0%A4%BF%E0%A4%A6%E0%A5%8D%E0%A4%A6%E0%A4%BE%E0%A4%B2%E0%A4%AF", "name": "\u0930\u093e\u091c\u0915\u093f\u092f \u092e\u093e\u0927\u094d\u092f\u092e\u093f\u0915 \u0935\u093f\u0926\u094d\u0926\u093e\u0932\u092f", "category": "No reviews", "street": "Secondary school \u00b7 \ue934 \u00b7 C8GF+2F3", "phone": "", "website": "", "rating": "", "review_count": "", "maps_url": "https://www.google.com/maps/place/%E0%A4%B0%E0%A4%BE%E0%A4%9C%E0%A4%95%E0%A4%BF%E0%A4%AF+%E0%A4%AE%E0%A4%BE%E0%A4%A7%E0%A5%8D%E0%A4%AF%E0%A4%AE%E0%A4%BF%E0%A4%95+%E0%A4%B5%E0%A4%BF%E0%A4%A6%E0%A5%8D%E0%A4%A6%E0%A4%BE%E0%A4%B2%E0%A4%AF/data=!4m7!3m6!1s0x3968fa32a8495793:0xbd4f18e12e82c3a3!8m2!3d25.4250228!4d74.3236655!16s%2Fg%2F11f53nc949!19sChIJk1dJqDL6aDkRo8OCLuEYT70?authuser=0&hl=en&rclk=1", "latitude": 25.4250228, "longitude": 74.3236655}, {"place_id": "%E0%A4%B0%E0%A4%BE%E0%A4%9C%E0%A4%95%E0%A5%80%E0%A4%AF+%E0%A4%86%E0%A4%A6%E0%A4%B0%E0%A5%8D%E0%A4%B6+%E0%A4%89%E0%A4%9A%E0%A5%8D%E0%A4%9A+%E0%A4%AE%E0%A4%BE%E0%A4%A7%E0%A5%8D%E0%A4%AF%E0%A4%AE%E0%A4%BF%E0%A4%95+%E0%A4%B5%E0%A4%BF%E0%A4%A6%E0%A5%8D%E0%A4%AF%E0%A4%BE%E0%A4%B2%E0%A4%AF+%E0%A4%B2%E0%A5%87%E0%A4%B8%E0%A4%B5%E0%A4%BE", "name": "\u0930\u093e\u091c\u0915\u0940\u092f \u0906\u0926\u0930\u094d\u0936 \u0909\u091a\u094d\u091a \u092e\u093e\u0927\u094d\u092f\u092e\u093f\u0915 \u0935\u093f\u0926\u094d\u092f\u093e\u0932\u092f \u0932\u0947\u0938\u0935\u093e", "category": "No reviews", "street": "Secondary school \u00b7 \ue934 \u00b7 C96J+98R", "phone": "", "website": "", "rating": "", "review_count": "", "maps_url": "https://www.google.com/maps/place/%E0%A4%B0%E0%A4%BE%E0%A4%9C%E0%A4%95%E0%A5%80%E0%A4%AF+%E0%A4%86%E0%A4%A6%E0%A4%B0%E0%A5%8D%E0%A4%B6+%E0%A4%89%E0%A4%9A%E0%A5%8D%E0%A4%9A+%E0%A4%AE%E0%A4%BE%E0%A4%A7%E0%A5%8D%E0%A4%AF%E0%A4%AE%E0%A4%BF%E0%A4%95+%E0%A4%B5%E0%A4%BF%E0%A4%A6%E0%A5%8D%E0%A4%AF%E0%A4%BE%E0%A4%B2%E0%A4%AF+%E0%A4%B2%E0%A5%87%E0%A4%B8%E0%A4%B5%E0%A4%BE/data=!4m7!3m6!1s0x3968fb0029e734ef:0xf49cea32059a4c67!8m2!3d25.4109875!4d74.3807694!16s%2Fg%2F11vwnbsy6j!19sChIJ7zTnKQD7aDkRZ0yaBTLqnPQ?authuser=0&hl=en&rclk=1", "latitude": 25.4109875, "longitude": 74.3807694}, {"place_id": "Govt+girls+sr+sec+school+jogras", "name": "Govt girls sr sec school jogras", "category": "No reviews", "street": "High school \u00b7 \ue934 \u00b7 97JV+5QP", "phone": "", "website": "", "rating": "", "review_count": "", "maps_url": "https://www.google.com/maps/place/Govt+girls+sr+sec+school+jogras/data=!4m7!3m6!1s0x3968f9e66fe7f62d:0xa78904f9e65e2c07!8m2!3d25.3804512!4d74.2944423!16s%2Fg%2F11st9v9r12!19sChIJLfbnb-b5aDkRByxe5vkEiac?authuser=0&hl=en&rclk=1", "latitude": 25.3804512, "longitude": 74.2944423}, {"place_id": "Government+Primary+School+Bhilo+Ka+Khera", "name": "Government Primary School Bhilo Ka Khera", "category": "No reviews", "street": "Primary school \u00b7 \ue934 \u00b7 C8PH+G6V", "phone": "", "website": "", "rating": "", "review_count": "", "maps_url": "https://www.google.com/maps/place/Government+Primary+School+Bhilo+Ka+Khera/data=!4m7!3m6!1s0x3968fba65b2389f5:0xdaf6eceb594246c1!8m2!3d25.4363703!4d74.3280375!16s%2Fg%2F11hygk_v9f!19sChIJ9YkjW6b7aDkRwUZCWevs9to?authuser=0&hl=en&rclk=1", "latitude": 25.4363703, "longitude": 74.3280375}, {"place_id": "government+primary+school,+Nahari+,+Raipur,+Bhilwara", "name": "government primary school, Nahari , Raipur, Bhilwara", "category": "No reviews", "street": "Primary school \u00b7 \ue934 \u00b7 97HM+WH2Open \u00b7 Closes 4\u202fpm", "phone": "", "website": "", "rating": "", "review_count": "", "maps_url": "https://www.google.com/maps/place/government+primary+school,+Nahari+,+Raipur,+Bhilwara/data=!4m7!3m6!1s0x3968f9debde25797:0x7aa38dbcc98083bf!8m2!3d25.3797501!4d74.2838953!16s%2Fg%2F11h9yss_8t!19sChIJl1fivd75aDkRv4OAybyNo3o?authuser=0&hl=en&rclk=1", "latitude": 25.3797501, "longitude": 74.2838953}, {"place_id": "Government+Senior+Secondary+School", "name": "Government Senior Secondary School", "category": "No reviews", "street": "Higher secondary school \u00b7 \ue934 \u00b7 C77P+QP6Closed \u00b7 Opens 7\u202fpm", "phone": "", "website": "", "rating": "", "review_count": "", "maps_url": "https://www.google.com/maps/place/Government+Senior+Secondary+School/data=!4m7!3m6!1s0x3968f9a23ff0ad01:0xbbc82408371dd8de!8m2!3d25.4144096!4d74.2867747!16s%2Fg%2F11gfn_jby9!19sChIJAa3wP6L5aDkR3tgdNwgkyLs?authuser=0&hl=en&rclk=1", "latitude": 25.4144096, "longitude": 74.2867747}, {"place_id": "Govt+Sr+Sec+School+Bavlas+Mandal+%28214568%29", "name": "Govt Sr Sec School Bavlas Mandal (214568)", "category": "No reviews", "street": "Secondary school \u00b7 \ue934 \u00b7 983G+986Open \u00b7 Closes 1\u202fpm", "phone": "", "website": "", "rating": "", "review_count": "", "maps_url": "https://www.google.com/maps/place/Govt+Sr+Sec+School+Bavlas+Mandal+%28214568%29/data=!4m7!3m6!1s0x3968f1a0d77b6db7:0x3de36da4b13491df!8m2!3d25.3534013!4d74.3257532!16s%2Fg%2F11f5v7yrff!19sChIJt21716DxaDkR35E0saRt4z0?authuser=0&hl=en&rclk=1", "latitude": 25.3534013, "longitude": 74.3257532}, {"place_id": "GOVT+PRIMARY+SCHOOL+ADARSHNAGAR", "name": "GOVT PRIMARY SCHOOL ADARSHNAGAR", "category": "No reviews", "street": "Elementary school \u00b7 C99X+W3J", "phone": "", "website": "", "rating": "", "review_count": "", "maps_url": "https://www.google.com/maps/place/GOVT+PRIMARY+SCHOOL+ADARSHNAGAR/data=!4m7!3m6!1s0x3968fb007561228d:0x5ab11005f81b5763!8m2!3d25.4198358!4d74.3974115!16s%2Fg%2F11y3wqc53_!19sChIJjSJhdQD7aDkRY1cb-AUQsVo?authuser=0&hl=en&rclk=1", "latitude": 25.4198358, "longitude": 74.3974115}, {"place_id": "Government+senior+secondary+school+Nahari,+Raipur+Bhilwara", "name": "Government senior secondary school Nahari, Raipur Bhilwara", "category": "No reviews", "street": "High school \u00b7 \ue934 \u00b7 97HM+4X8", "phone": "", "website": "", "rating": "", "review_count": "", "maps_url": "https://www.google.com/maps/place/Government+senior+secondary+school+Nahari,+Raipur+Bhilwara/data=!4m7!3m6!1s0x3968f9af0628526f:0x8faba8ca905bda74!8m2!3d25.377776!4d74.2849509!16s%2Fg%2F11s3xbbp_9!19sChIJb1IoBq_5aDkRdNpbkMqoq48?authuser=0&hl=en&rclk=1", "latitude": 25.377776, "longitude": 74.2849509}, {"place_id": "Govt.+Sr.+Sec.+School+Bagor", "name": "Govt. Sr. Sec. School Bagor", "category": "No reviews", "street": "Secondary school \u00b7 \ue934 \u00b7 994H+5FPOpen \u00b7 Closes 2\u202fpm", "phone": "", "website": "", "rating": "", "review_count": "", "maps_url": "https://www.google.com/maps/place/Govt.+Sr.+Sec.+School+Bagor/data=!4m7!3m6!1s0x3968f046c8bcf607:0x2b9eb9224e8e9ea9!8m2!3d25.3554613!4d74.3786882!16s%2Fg%2F11cn3j6l35!19sChIJB_a8yEbwaDkRqZ6OTiK5nis?authuser=0&hl=en&rclk=1", "latitude": 25.3554613, "longitude": 74.3786882}, {"place_id": "G.+S.+S.+School+Gadri+Khera+Nahri", "name": "G. S. S. School Gadri Khera Nahri", "category": "No reviews", "street": "Secondary school \u00b7 \ue934 \u00b7 97CP+86X", "phone": "", "website": "", "rating": "", "review_count": "", "maps_url": "https://www.google.com/maps/place/G.+S.+S.+School+Gadri+Khera+Nahri/data=!4m7!3m6!1s0x3968f75dee5101a9:0xa88efc28ce3667b3!8m2!3d25.3708537!4d74.2856089!16s%2Fg%2F11rcblk9ry!19sChIJqQFR7l33aDkRs2c2zij8jqg?authuser=0&hl=en&rclk=1", "latitude": 25.3708537, "longitude": 74.2856089}, {"place_id": "LAKSHYA+INTERNATIONAL+SCHOOL", "name": "LAKSHYA INTERNATIONAL SCHOOL", "category": "No reviews", "street": "General education school \u00b7 \ue934 \u00b7 MDR 80", "phone": "Open \u00b7 Closes 12:30\u202fpm \u00b7 097723 75756", "website": "", "rating": "", "review_count": "", "maps_url": "https://www.google.com/maps/place/LAKSHYA+INTERNATIONAL+SCHOOL/data=!4m7!3m6!1s0x3968f1b6b8b896e7:0x231ad84beed7cf4e!8m2!3d25.3608587!4d74.3881032!16s%2Fg%2F11h7kt9z30!19sChIJ55a4uLbxaDkRTs_X7kvYGiM?authuser=0&hl=en&rclk=1", "latitude": 25.3608587, "longitude": 74.3881032}, {"place_id": "govet.+sec.school.+adsipura", "name": "govet. sec.school. adsipura", "category": "No reviews", "street": "Secondary school \u00b7 9943+GHM", "phone": "077929 34619", "website": "", "rating": "", "review_count": "", "maps_url": "https://www.google.com/maps/place/govet.+sec.school.+adsipura/data=!4m7!3m6!1s0x3968f0f464142e27:0x1d3bbaf13e2591ee!8m2!3d25.3563255!4d74.3539182!16s%2Fg%2F11fy9dksvv!19sChIJJy4UZPTwaDkR7pElPvG6Ox0?authuser=0&hl=en&rclk=1", "latitude": 25.3563255, "longitude": 74.3539182}, {"place_id": "Prem+devi+Baidh+Government+girls+senior+secondary+school+Bagor", "name": "Prem devi Baidh Government girls senior secondary school Bagor", "category": "No reviews", "street": "High school \u00b7 MDR 80Open \u00b7 Closes 1:05\u202fpm", "phone": "", "website": "", "rating": "", "review_count": "", "maps_url": "https://www.google.com/maps/place/Prem+devi+Baidh+Government+girls+senior+secondary+school+Bagor/data=!4m7!3m6!1s0x3968f1cc46fbe477:0xa4d16c78acf7f318!8m2!3d25.358161!4d74.3845869!16s%2Fg%2F11v9gf637b!19sChIJd-T7RszxaDkRGPP3rHhs0aQ?authuser=0&hl=en&rclk=1", "latitude": 25.358161, "longitude": 74.3845869}]}