{"timestamp": 1773730591.565572, "keyword": "IT company", "location": "delhi", "cell_idx": 263, "results": [{"place_id": "0x390d1d95931171db:0xf4c24d49d831b27", "name": "Muniwar Technologies Private Limited", "category": "Software company", "street": "2nd Floor", "city": "Hanuman Mandir Market", "phone": "01143050611", "website": "https://www.muniwar.com/", "rating": 4.4, "review_count": "", "latitude": 28.557070699999997, "longitude": 77.1732794, "maps_url": "https://www.google.com/maps/place/?q=place_id:0x390d1d95931171db:0xf4c24d49d831b27"}, {"place_id": "0x8a77b9133d00e1d5:0xdc22385e31357395", "name": "Codologi IT Solutions Pvt Ltd", "category": "Software company", "street": "F-2/401", "city": "near Budh Vihar Street", "phone": "09999687725", "website": "https://codologi.in/", "rating": 5, "review_count": "", "latitude": 28.553921199999998, "longitude": 77.171915, "maps_url": "https://www.google.com/maps/place/?q=place_id:0x8a77b9133d00e1d5:0xdc22385e31357395"}, {"place_id": "0x390d1d9ce0eaada3:0xc5a1a0a2458099e3", "name": "CODENCREATIVE TECH PVT LTD", "category": "Software company", "street": "DDA Flat", "city": "RBI Officers Colony, Vasant Vihar", "phone": "09717047610", "website": "https://codencreative.com/", "rating": 4.9, "review_count": "", "latitude": 28.563302099999998, "longitude": 77.1519732, "maps_url": "https://www.google.com/maps/place/?q=place_id:0x390d1d9ce0eaada3:0xc5a1a0a2458099e3"}, {"place_id": "0x390d1d082306ddf1:0xa07970337e981229", "name": "Lumina Infotech", "category": "Software company", "street": "BD/1st", "city": "401/1, Budh Vihar St", "phone": "", "website": "https://www.luminainfotech.com/", "rating": 5, "review_count": "", "latitude": 28.551873999999998, "longitude": 77.17046979999999, "maps_url": "https://www.google.com/maps/place/?q=place_id:0x390d1d082306ddf1:0xa07970337e981229"}, {"place_id": "0x390ce458d0000001:0xf2123bd299ec4501", "name": "IT Company India", "category": "Software company", "street": "D56", "city": "D Block, Sector 10", "phone": "09999244854", "website": "https://www.itcompanyindia.in/", "rating": 4.7, "review_count": "", "latitude": 28.589917699999997, "longitude": 77.3351153, "maps_url": "https://www.google.com/maps/place/?q=place_id:0x390ce458d0000001:0xf2123bd299ec4501"}, {"place_id": "0x390d1d94ffc05fbd:0x67954500e48683e8", "name": "Complete Digital Solutions | Sahish Technologies LLP", "category": "Software company", "street": "404 4th floor M92/1", "city": "Munirka", "phone": "08826635880", "website": "https://www.sahish.com/", "rating": 4.9, "review_count": "", "latitude": 28.556879199999997, "longitude": 77.1731178, "maps_url": "https://www.google.com/maps/place/?q=place_id:0x390d1d94ffc05fbd:0x67954500e48683e8"}, {"place_id": "0x390d1daf5bbb6d71:0xd493e8d457a28388", "name": "DPM IT SOLUTIONS", "category": "Software company", "street": "2nd floor, madangiri", "city": "111, E-2", "phone": "09650413450", "website": "https://dpmitsolutions.com/", "rating": 5, "review_count": "", "latitude": 28.565620799999998, "longitude": 77.16005679999999, "maps_url": "https://www.google.com/maps/place/?q=place_id:0x390d1daf5bbb6d71:0xd493e8d457a28388"}, {"place_id": "0x390ce3c153b89811:0xe7a279685777e9ca", "name": "IT Company", "category": "Automation company", "street": "A-14", "city": "near iskcon temple", "phone": "", "website": "http://www.opuswiz.com/", "rating": 3, "review_count": "", "latitude": 28.557167, "longitude": 77.25424819999999, "maps_url": "https://www.google.com/maps/place/?q=place_id:0x390ce3c153b89811:0xe7a279685777e9ca"}, {"place_id": "0x390d1c32a16c2629:0xa37e7b027558a29e", "name": "Avalon Information Systems Pvt. Ltd.", "category": "Software company", "street": "Plot No. 7, Institutional Area Phase II, 3rd Floor", "city": "Vasant Kunj", "phone": "09319391086", "website": "https://www.avaloninfosys.com/", "rating": 3.7, "review_count": "", "latitude": 28.5431746, "longitude": 77.146245, "maps_url": "https://www.google.com/maps/place/?q=place_id:0x390d1c32a16c2629:0xa37e7b027558a29e"}, {"place_id": "0x390d1d94ffc05fbd:0x4f2b17f82687846f", "name": "Accore Technologies", "category": "Website designer", "street": "Bank St", "city": "near Canara Bank", "phone": "09560449918", "website": "https://accoretechnologies.com/", "rating": 4.9, "review_count": "", "latitude": 28.555705999999997, "longitude": 77.1748403, "maps_url": "https://www.google.com/maps/place/?q=place_id:0x390d1d94ffc05fbd:0x4f2b17f82687846f"}, {"place_id": "0x390d1d86a4f12173:0x3a6b42ea6f4b8260", "name": "Softvanz Technologies Private Limited", "category": "Software company", "street": "Somdutt Chamber 1", "city": "BT-22/9", "phone": "", "website": "https://softvanz.com/", "rating": 5, "review_count": "", "latitude": 28.567948899999998, "longitude": 77.1889269, "maps_url": "https://www.google.com/maps/place/?q=place_id:0x390d1d86a4f12173:0x3a6b42ea6f4b8260"}, {"place_id": "0x390ce1fb44618b65:0x8e06b2a6128352d1", "name": "Acropolis Infotech - Delhi Office", "category": "Software company", "street": "metro station gate", "city": "55, 2nd Floor, Lane 2", "phone": "09999876593", "website": "https://www.acropolisinfotech.com/", "rating": 4.6, "review_count": "", "latitude": 28.518907, "longitude": 77.2015435, "maps_url": "https://www.google.com/maps/place/?q=place_id:0x390ce1fb44618b65:0x8e06b2a6128352d1"}, {"place_id": "0x390d1df079759d1f:0x8bfa70033f6c672a", "name": "NR Technoserve Pvt. Ltd.", "category": "Software company", "street": "133, Katwaria Sarai", "city": "Phase-2, Qutab Institutional Area", "phone": "07289096762", "website": "http://www.nrtechnoserve.co.in/", "rating": 4.4, "review_count": "", "latitude": 28.5413306, "longitude": 77.18495519999999, "maps_url": "https://www.google.com/maps/place/?q=place_id:0x390d1df079759d1f:0x8bfa70033f6c672a"}, {"place_id": "0x390ce3ad10000061:0xeff7e6017a22cce7", "name": "Alpinesoft IT Solutions Authorized Google Workspace Reseller", "category": "Software company", "street": "162/9 Ist Floor, KIshangarh - Gaushala Marg", "city": "Lakhi Nath Kuti, Mehrauli, Vasant Kunj", "phone": "09999011157", "website": "https://www.alpinesoftit.com/", "rating": 4.3, "review_count": "", "latitude": 28.515394399999998, "longitude": 77.16460359999999, "maps_url": "https://www.google.com/maps/place/?q=place_id:0x390ce3ad10000061:0xeff7e6017a22cce7"}, {"place_id": "0x390d165555555555:0xf57c20f7d07d8fd1", "name": "Teckinfo Solutions Pvt Ltd", "category": "Software company", "street": "1/1 BA, 3rd Floor, Mohammadpur,", "city": "Bhikaji Cama Place", "phone": "01149605500", "website": "https://www.teckinfo.com/", "rating": 4.6, "review_count": "", "latitude": 28.566004099999997, "longitude": 77.187579, "maps_url": "https://www.google.com/maps/place/?q=place_id:0x390d165555555555:0xf57c20f7d07d8fd1"}, {"place_id": "0x390d1da5fb71857f:0x4ab9a25a49e38e5e", "name": "Arixpower Technologies | website development | mobile app development |digital marketing |seo", "category": "Software company", "street": "249", "city": "near Parking", "phone": "09651639808", "website": "", "rating": 5, "review_count": "", "latitude": 28.557499399999998, "longitude": 77.1708427, "maps_url": "https://www.google.com/maps/place/?q=place_id:0x390d1da5fb71857f:0x4ab9a25a49e38e5e"}, {"place_id": "0x390d1d9680764375:0xc892495413ac100c", "name": "Deft Infosystems Private Limited", "category": "Software company", "street": "METRO Gate Number 3", "city": "304, Pratap Complex, G-92", "phone": "09310116077", "website": "http://www.deftinfosystems.com/", "rating": 5, "review_count": "", "latitude": 28.5566155, "longitude": 77.17399619999999, "maps_url": "https://www.google.com/maps/place/?q=place_id:0x390d1d9680764375:0xc892495413ac100c"}, {"place_id": "0x390cfde27d1f7347:0xa3546b35263a813a", "name": "Brian Soft Global Services", "category": "Software company", "street": "1st Floor", "city": "Upstairs Of Bank Of Baroda", "phone": "09007144778", "website": "https://www.briansoftglobalservices.com/", "rating": 5, "review_count": "", "latitude": 28.5576603, "longitude": 77.1726055, "maps_url": "https://www.google.com/maps/place/?q=place_id:0x390cfde27d1f7347:0xa3546b35263a813a"}, {"place_id": "0x2a72b8b69d7b6493:0x11251466d4d34cac", "name": "WebZonal IT Company", "category": "Website designer", "street": "Wz-258/2-3, D Block Rd", "city": "Khazan Basti, Nangal Raya, Janakpuri", "phone": "09811170903", "website": "http://webzonal.com/", "rating": 5, "review_count": "", "latitude": 28.6122102, "longitude": 77.11159549999999, "maps_url": "https://www.google.com/maps/place/?q=place_id:0x2a72b8b69d7b6493:0x11251466d4d34cac"}, {"place_id": "0x390d1f5abfb25fe1:0x7d9c4d5e159f2955", "name": "Jaimru Technology Pvt Ltd", "category": "Software company", "street": "WARD NO. 2", "city": "Plot No. 178 M 33 A/1", "phone": "07838153420", "website": "https://www.jaimru.com/", "rating": 4.9, "review_count": "", "latitude": 28.524347499999998, "longitude": 77.1731889, "maps_url": "https://www.google.com/maps/place/?q=place_id:0x390d1f5abfb25fe1:0x7d9c4d5e159f2955"}, {"place_id": "0x390ce2305c00002d:0x9f7efbacdc0d8271", "name": "ICO WebTech Pvt. Ltd. - Website Designing Company in Delhi", "category": "Website designer", "street": "J E 5, Ground Floor, Khirki Extension, Malviya Nagar", "city": "New Delhi, Delhi 110017", "phone": "08447380262", "website": "https://www.icowebsolutions.com/", "rating": 4.6, "review_count": "", "latitude": 28.535594, "longitude": 77.21577099999999, "maps_url": "https://www.google.com/maps/place/?q=place_id:0x390ce2305c00002d:0x9f7efbacdc0d8271"}, {"place_id": "0x390ce5fdcc79e755:0x309ce99251b84ef6", "name": "Optyminds IT Solutions - Top AI and IT company I Best Digital agency in Noida | Delhi NCR | India", "category": "Software company", "street": "1st Floor", "city": "B-70", "phone": "08929075975", "website": "https://optyminds.com/", "rating": 4.9, "review_count": "", "latitude": 28.584679599999998, "longitude": 77.3135042, "maps_url": "https://www.google.com/maps/place/?q=place_id:0x390ce5fdcc79e755:0x309ce99251b84ef6"}, {"place_id": "0x390d02994de5e515:0xd908bc03409a0d37", "name": "Himalayan IT Solutions | Best Website Designing Company in Delhi | SEO/Digital Marketing Company in Delhi NCR, India", "category": "Software company", "street": "61/4255, Padam Singh Rd", "city": "Block 29, Block 1, Regar Pura, Karol Bagh", "phone": "09899098509", "website": "http://www.himalayanitsolutions.com/", "rating": 3.9, "review_count": "", "latitude": 28.649673999999997, "longitude": 77.186599, "maps_url": "https://www.google.com/maps/place/?q=place_id:0x390d02994de5e515:0xd908bc03409a0d37"}, {"place_id": "0x390d1d85e272f34f:0x8c7369f31e3198f0", "name": "EkAnek Spaces - Coworking Space & Business Centre in Vasant Vihar, South Delhi", "category": "Corporate office", "street": "1st Floor", "city": "63D", "phone": "09910204380", "website": "https://spaces.ekanek.net/", "rating": 4.4, "review_count": "", "latitude": 28.5572511, "longitude": 77.1649814, "maps_url": "https://www.google.com/maps/place/?q=place_id:0x390d1d85e272f34f:0x8c7369f31e3198f0"}, {"place_id": "0x390d1be7f1a44f95:0x84524a5425f8930d", "name": "InfraDost Technologies Pvt Ltd.- Microsoft Adobe Corel Draw & Security Solution Provider", "category": "Software company", "street": "Gurgaon - Delhi Expy", "city": "Block B, Mahipalpur Village, Mahipalpur", "phone": "08287792542", "website": "http://www.infradost.com/", "rating": 4.6, "review_count": "", "latitude": 28.5485743, "longitude": 77.1264697, "maps_url": "https://www.google.com/maps/place/?q=place_id:0x390d1be7f1a44f95:0x84524a5425f8930d"}, {"place_id": "0x390ce26dc4d4ba2d:0x9486a6d620e379f9", "name": "Akal Information Systems Ltd.", "category": "Software company", "street": "Tower J, World Trade Center", "city": "103", "phone": "01146503545", "website": "https://www.akalinfo.com/", "rating": 3.9, "review_count": "", "latitude": 28.567935499999997, "longitude": 77.1923202, "maps_url": "https://www.google.com/maps/place/?q=place_id:0x390ce26dc4d4ba2d:0x9486a6d620e379f9"}, {"place_id": "0x390d1dbfbc476a45:0x18e949f73698de4", "name": "R. Computer Clinic", "category": "Computer repair service", "street": "401/1 ABC, Munirka, Baba Gangnath Marg", "city": "Main Gate", "phone": "09910538597", "website": "https://www.rcomputerclinic.in/", "rating": 4.5, "review_count": "", "latitude": 28.5516743, "longitude": 77.1698888, "maps_url": "https://www.google.com/maps/place/?q=place_id:0x390d1dbfbc476a45:0x18e949f73698de4"}, {"place_id": "0x390d1db0aef40171:0xb748a2e6079dd53d", "name": "YB INFORMATICS", "category": "Computer support and services", "street": "43, Poorvi Marg", "city": "Block A, Vasant Vihar", "phone": "09650920040", "website": "http://www.ybinformatics.com/", "rating": 5, "review_count": "", "latitude": 28.560817399999998, "longitude": 77.1666408, "maps_url": "https://www.google.com/maps/place/?q=place_id:0x390d1db0aef40171:0xb748a2e6079dd53d"}, {"place_id": "0x390ce3c50d455555:0x625e4cf2def0b6ac", "name": "Infonative Solutions Limited", "category": "Computer support and services", "street": "107, 108", "city": "DLF South Court", "phone": "08448141818", "website": "https://infonative.net/", "rating": 4.7, "review_count": "", "latitude": 28.5274255, "longitude": 77.2209031, "maps_url": "https://www.google.com/maps/place/?q=place_id:0x390ce3c50d455555:0x625e4cf2def0b6ac"}, {"place_id": "0x390d1db6a1809e83:0x8893414d6a439a39", "name": "KST Systems", "category": "Software company", "street": "C-453/1 Kusum Pur Pahari", "city": "Vasant Kunj, Delhi 110057", "phone": "09810253045", "website": "", "rating": 1, "review_count": "", "latitude": 28.5531588, "longitude": 77.1546652, "maps_url": "https://www.google.com/maps/place/?q=place_id:0x390d1db6a1809e83:0x8893414d6a439a39"}, {"place_id": "0x390d1da4cc4d2109:0x78c943f244e07d0d", "name": "AcuittyTech", "category": "Software company", "street": "A 10/3 LGF", "city": "Block A, Vasant Vihar", "phone": "01143550198", "website": "http://acuittytech.com/", "rating": 4, "review_count": "", "latitude": 28.5611292, "longitude": 77.1637994, "maps_url": "https://www.google.com/maps/place/?q=place_id:0x390d1da4cc4d2109:0x78c943f244e07d0d"}, {"place_id": "0x390d1dc3ce749851:0xc80f9b86c994f0c0", "name": "Casca E-Connect Private Limited", "category": "Manufacturer", "street": "F-92/1 Shanti Swaroop Complex, 4th Floor", "city": "Munirka", "phone": "09971062561", "website": "https://www.cascaeconnect.com/", "rating": 5, "review_count": "", "latitude": 28.556516499999997, "longitude": 77.174064, "maps_url": "https://www.google.com/maps/place/?q=place_id:0x390d1dc3ce749851:0xc80f9b86c994f0c0"}, {"place_id": "0x390d1db0acb1fa87:0x23b20ede14955dc", "name": "Digital Media Conversions", "category": "Website designer", "street": "CGHS Colony, Vasant Vihar", "city": "New Delhi, Delhi 110057", "phone": "07982285967", "website": "https://digitalmediaconversions.com/", "rating": 4.8, "review_count": "", "latitude": 28.5548054, "longitude": 77.1595124, "maps_url": "https://www.google.com/maps/place/?q=place_id:0x390d1db0acb1fa87:0x23b20ede14955dc"}, {"place_id": "0x390d1dc8e1c70ee3:0x3d8673eb9d295b8e", "name": "Oil and Natural Gas Corporation Limited (ONGC)", "category": "Oil & natural gas company", "street": "5, Nelson Mandela Marg", "city": "Vasant Kunj II, Vasant Kunj", "phone": "01126750111", "website": "https://www.ongcindia.com/wps/wcm/connect/en/home/", "rating": 4.7, "review_count": "", "latitude": 28.5444951, "longitude": 77.1572075, "maps_url": "https://www.google.com/maps/place/?q=place_id:0x390d1dc8e1c70ee3:0x3d8673eb9d295b8e"}, {"place_id": "0x390d191598f48ef3:0x70991b4ff870f05d", "name": "Shree Partners LLC", "category": "Software company", "street": "1, Tower A, Building, Cyber City", "city": "Corporate Edge Level", "phone": "01246728815", "website": "https://www.shreepartners.com/", "rating": 4.3, "review_count": "", "latitude": 28.4936018, "longitude": 77.088325, "maps_url": "https://www.google.com/maps/place/?q=place_id:0x390d191598f48ef3:0x70991b4ff870f05d"}, {"place_id": "0x390d1ed3c6e9f579:0x322eccdb00f350d2", "name": "Techjockey", "category": "Software company", "street": "Ground floor, Habitat India", "city": "C-3", "phone": "01142213003", "website": "https://www.techjockey.com/", "rating": 4, "review_count": "", "latitude": 28.536615299999998, "longitude": 77.1902978, "maps_url": "https://www.google.com/maps/place/?q=place_id:0x390d1ed3c6e9f579:0x322eccdb00f350d2"}, {"place_id": "0x390ce21be933204d:0x44d1899d97aab2a", "name": "Apppl Combine", "category": "Advertising agency", "street": "QN 46/165", "city": "Munirka Vihar, Munirka", "phone": "07863011011", "website": "", "rating": 4.9, "review_count": "", "latitude": 28.553690099999997, "longitude": 77.1675423, "maps_url": "https://www.google.com/maps/place/?q=place_id:0x390ce21be933204d:0x44d1899d97aab2a"}, {"place_id": "0x390d1d4259dfca13:0x84ec6b01b088fefe", "name": "BPO CONVERGENCE PVT LTD Corporate", "category": "BPO Company", "street": "FPAI Building, 2nd Floor, PLOT# 10", "city": "Sector 4 R K Puram", "phone": "", "website": "http://bpoconvergence.com/", "rating": 4.8, "review_count": "", "latitude": 28.5566377, "longitude": 77.1761219, "maps_url": "https://www.google.com/maps/place/?q=place_id:0x390d1d4259dfca13:0x84ec6b01b088fefe"}, {"place_id": "0x390ce3d606c913ef:0xd246bd5631eb2cad", "name": "Delvetech", "category": "Software company", "street": "87A/1, 3rd Floor, Opp. Block N-115, G.K-1, Near Moolchand Merto", "city": "Block B, Zamrudpur, Greater Kailash", "phone": "09873895154", "website": "http://www.delvetech.co.in/", "rating": 4.1, "review_count": "", "latitude": 28.5570597, "longitude": 77.2356981, "maps_url": "https://www.google.com/maps/place/?q=place_id:0x390ce3d606c913ef:0xd246bd5631eb2cad"}, {"place_id": "0x390ce45bcd61048f:0x5f6a5602f4155df7", "name": "JK Technosoft Limited", "category": "Software company", "street": "F", "city": "3", "phone": "01204606300", "website": "https://jktech.com/", "rating": 4.2, "review_count": "", "latitude": 28.5802509, "longitude": 77.31793329999999, "maps_url": "https://www.google.com/maps/place/?q=place_id:0x390ce45bcd61048f:0x5f6a5602f4155df7"}, {"place_id": "0x390d1dbd84000001:0x635da82644e14112", "name": "iSoftech Solutions", "category": "Website designer", "street": "401-A", "city": "Rama Market, Munirka", "phone": "09310419123", "website": "http://isoftechsolutions.com/", "rating": 5, "review_count": "", "latitude": 28.558064899999998, "longitude": 77.1707273, "maps_url": "https://www.google.com/maps/place/?q=place_id:0x390d1dbd84000001:0x635da82644e14112"}, {"place_id": "0x390ce243aa6c679d:0xe3be43b453423a71", "name": "Nouvel facilities Pvt Ltd", "category": "Corporate office", "street": "23, 2nd Floor, Community Center", "city": "Basant Lok, Vasant Vihar", "phone": "01147726666", "website": "http://www.nouvel.in/", "rating": 3.7, "review_count": "", "latitude": 28.559064199999998, "longitude": 77.1637669, "maps_url": "https://www.google.com/maps/place/?q=place_id:0x390ce243aa6c679d:0xe3be43b453423a71"}, {"place_id": "0x390ce1b9de54d101:0xc5184256693b27dd", "name": "LCK Technologies - Website designing development company South Delhi", "category": "Website designer", "street": "439 1st floor", "city": "438", "phone": "09891337955", "website": "https://lckdigitalmedia.in/", "rating": 4.9, "review_count": "", "latitude": 28.5089698, "longitude": 77.20114769999999, "maps_url": "https://www.google.com/maps/place/?q=place_id:0x390ce1b9de54d101:0xc5184256693b27dd"}, {"place_id": "0x390d1960c2b8367f:0xd2d30e45ac71acea", "name": "Vorombetech Solutions - Top IT & Digitalization Service Company in Gurugram", "category": "Software company", "street": "249", "city": "Phase IV, Udyog Vihar, Sector 19", "phone": "", "website": "https://vorombetech.com/", "rating": 4.8, "review_count": "", "latitude": 28.4941475, "longitude": 77.0808448, "maps_url": "https://www.google.com/maps/place/?q=place_id:0x390d1960c2b8367f:0xd2d30e45ac71acea"}, {"place_id": "0x390d195c26bfa369:0x69bd8efd2e3a31fe", "name": "Radical Minds Technologies Pvt. Ltd.", "category": "BPO Company", "street": "368", "city": "Phase II, Udyog Vihar, Sector 20", "phone": "01244338366", "website": "http://www.radicalminds.in/", "rating": 4.2, "review_count": "", "latitude": 28.506335099999998, "longitude": 77.0877546, "maps_url": "https://www.google.com/maps/place/?q=place_id:0x390d195c26bfa369:0x69bd8efd2e3a31fe"}, {"place_id": "0x390d1b94e83ad411:0x58872ab25a7bf4c", "name": "WebpromoTech", "category": "Software company", "street": "Wz-13, B-3", "city": "near Maruti Chowk", "phone": "09560381801", "website": "https://webpromotech.com/", "rating": 5, "review_count": "", "latitude": 28.5683872, "longitude": 77.16313389999999, "maps_url": "https://www.google.com/maps/place/?q=place_id:0x390d1b94e83ad411:0x58872ab25a7bf4c"}, {"place_id": "0x390d1e186527b451:0x3d552630d3703e21", "name": "Inca Infotech Technologies Pvt Ltd", "category": "Computer support and services", "street": "D-23/405, UGF", "city": "100 Feet Rd", "phone": "18008891907", "website": "https://www.incainfotech.com/", "rating": 3.6, "review_count": "", "latitude": 28.506226899999998, "longitude": 77.1850521, "maps_url": "https://www.google.com/maps/place/?q=place_id:0x390d1e186527b451:0x3d552630d3703e21"}, {"place_id": "0x390d1d88dcb890cd:0x79d9e70bd65ccefc", "name": "Prestige Pursuits Pvt Ltd", "category": "Corporate office", "street": "28", "city": "Basant Lok, Vasant Vihar", "phone": "18002674996", "website": "https://www.prestigegiftingdelights.com/", "rating": 3.2, "review_count": "", "latitude": 28.558411999999997, "longitude": 77.163854, "maps_url": "https://www.google.com/maps/place/?q=place_id:0x390d1d88dcb890cd:0x79d9e70bd65ccefc"}, {"place_id": "0x390d1d94ffc05fbd:0x959df91e9370aec6", "name": "One Direction Skill Solutions", "category": "Educational consultant", "street": "Munirka Flyover", "city": "Rama Market, Munirka", "phone": "09643027592", "website": "http://www.odssonline.com/", "rating": 4.8, "review_count": "", "latitude": 28.5583866, "longitude": 77.17120179999999, "maps_url": "https://www.google.com/maps/place/?q=place_id:0x390d1d94ffc05fbd:0x959df91e9370aec6"}, {"place_id": "0x390d1d187e8f18f3:0xd314c67dce19ccb4", "name": "IT Solutions", "category": "Computer service", "street": "Motilal Nehru Camp, Old JNU Campus, Munirka", "city": "New Delhi, Delhi 110067", "phone": "07838560178", "website": "https://computerservices365.wordpress.com/", "rating": 5, "review_count": "", "latitude": 28.5522942, "longitude": 77.178367, "maps_url": "https://www.google.com/maps/place/?q=place_id:0x390d1d187e8f18f3:0xd314c67dce19ccb4"}, {"place_id": "0x390d1dbca997176d:0x57e66bed722428a", "name": "Earthz Urban Spaces Pvt. Ltd.", "category": "Real Estate Builders & Construction Company", "street": "gate no 4", "city": "metro station", "phone": "09810313009", "website": "http://earthzurbanspaces.com/", "rating": 3.9, "review_count": "", "latitude": 28.5580338, "longitude": 77.1619972, "maps_url": "https://www.google.com/maps/place/?q=place_id:0x390d1dbca997176d:0x57e66bed722428a"}, {"place_id": "0x390d1da93576df9d:0xf3efeb3a9e6f8723", "name": "Ambition Host", "category": "Web hosting company", "street": "", "city": "", "phone": "08690909188", "website": "https://www.ambitionhost.in/", "rating": 3.5, "review_count": "", "latitude": 21.0680074, "longitude": 82.7525294, "maps_url": "https://www.google.com/maps/place/?q=place_id:0x390d1da93576df9d:0xf3efeb3a9e6f8723"}, {"place_id": "0x390d1d0f0f6cb853:0xf5c7f48321e806d9", "name": "ITRSP Technologies", "category": "Software company", "street": "A21", "city": "Basant Nagar, Vasant Vihar", "phone": "", "website": "https://itrsp.com/", "rating": "", "review_count": "", "latitude": 28.5747306, "longitude": 77.1583826, "maps_url": "https://www.google.com/maps/place/?q=place_id:0x390d1d0f0f6cb853:0xf5c7f48321e806d9"}, {"place_id": "0x28d0076b54fe0de9:0x4737fc4ba919f58b", "name": "KCJ Resources Private Limited", "category": "Computer support and services", "street": "100 A/5 Ground Floor, The", "city": "Capital Court", "phone": "09205222861", "website": "https://kcjresources.com/", "rating": 5, "review_count": "", "latitude": 28.556098499999997, "longitude": 77.1750941, "maps_url": "https://www.google.com/maps/place/?q=place_id:0x28d0076b54fe0de9:0x4737fc4ba919f58b"}, {"place_id": "0x390d1de4927b2a03:0x2533739c7b861d05", "name": "ONGC Videsh Ltd.", "category": "Corporate campus", "street": "Tower B", "city": "5, Nelson Mandela Marg", "phone": "01126129344", "website": "https://ongcvidesh.com/", "rating": 4.8, "review_count": "", "latitude": 28.544493199999998, "longitude": 77.15786229999999, "maps_url": "https://www.google.com/maps/place/?q=place_id:0x390d1de4927b2a03:0x2533739c7b861d05"}, {"place_id": "0x390d1dde7b4cdf11:0x1f654c53df3fdd92", "name": "Aone HR Services", "category": "Recruiter", "street": "35", "city": "Basant Lok, Vasant Vihar", "phone": "09312683206", "website": "http://www.aonehr.net/", "rating": 4.8, "review_count": "", "latitude": 28.558162199999998, "longitude": 77.1640417, "maps_url": "https://www.google.com/maps/place/?q=place_id:0x390d1dde7b4cdf11:0x1f654c53df3fdd92"}, {"place_id": "0x390d1d9617b17699:0x23d99593aa44a7f2", "name": "Alliance Telenet Pvt Ltd", "category": "Telecommunications service provider", "street": "313, IIIrd Floor", "city": "Munirka", "phone": "01126173000", "website": "http://alliancetelenet.com/", "rating": 3.6, "review_count": "", "latitude": 28.5572928, "longitude": 77.17239479999999, "maps_url": "https://www.google.com/maps/place/?q=place_id:0x390d1d9617b17699:0x23d99593aa44a7f2"}, {"place_id": "0x390d1e748ef61961:0x754ceb660996cfdb", "name": "ACS System Solutions", "category": "Software company", "street": "Kishangarh, Kishangarh Village, Vasant Kunj", "city": "New Delhi, Delhi 110070", "phone": "01149858620", "website": "http://acssystem.in/", "rating": 3.4, "review_count": "", "latitude": 28.522178699999998, "longitude": 77.1692609, "maps_url": "https://www.google.com/maps/place/?q=place_id:0x390d1e748ef61961:0x754ceb660996cfdb"}, {"place_id": "0x390ce1bef0c8c071:0xb0a64e46c6405fc6", "name": "Tech rise dynamics", "category": "Website designer", "street": "293, Lane-2, Westend Marg", "city": "near Saket Metro Station", "phone": "08750557052", "website": "https://www.techrisedynamics.com/", "rating": 5, "review_count": "", "latitude": 28.5177321, "longitude": 77.1986237, "maps_url": "https://www.google.com/maps/place/?q=place_id:0x390ce1bef0c8c071:0xb0a64e46c6405fc6"}, {"place_id": "0x390ce23eeab015ab:0x92d6a7e8dbc46e1a", "name": "Odyssey Website Development Company", "category": "Website designer", "street": "B-59", "city": "Block B, Soami Nagar South, Soami Nagar", "phone": "09654486464", "website": "http://odysseyin.com/?utm_source=GMB&utm_medium=Organic&utm_term=Odyssey&utm_content=Listing&utm_campaign=GMB1", "rating": 3.6, "review_count": "", "latitude": 28.541823599999997, "longitude": 77.2262008, "maps_url": "https://www.google.com/maps/place/?q=place_id:0x390ce23eeab015ab:0x92d6a7e8dbc46e1a"}, {"place_id": "0x390d1d94ffc05fbd:0xb6e11eb0e17c1deb", "name": "Planet Packers and Movers Delhi - Best Packers and Movers in South Delhi", "category": "Packaging company", "street": "B-263", "city": "Baba Gangnath Market, Munirka", "phone": "09871318494", "website": "https://www.planetpackersmovers.com/", "rating": 4.9, "review_count": "", "latitude": 28.5549368, "longitude": 77.1716398, "maps_url": "https://www.google.com/maps/place/?q=place_id:0x390d1d94ffc05fbd:0xb6e11eb0e17c1deb"}, {"place_id": "0x390d1d841aaaaaab:0xa32856a97de4096b", "name": "BI Biotech India Pvt. Ltd. (Corporate Office)", "category": "Biotechnology company", "street": "328", "city": "Ansal Chamber-2", "phone": "01126101271", "website": "http://www.biotechindia.com/", "rating": 3.9, "review_count": "", "latitude": 28.5677649, "longitude": 77.187382, "maps_url": "https://www.google.com/maps/place/?q=place_id:0x390d1d841aaaaaab:0xa32856a97de4096b"}, {"place_id": "0x390d1dbc6fffffff:0x470ee9dfa48102cf", "name": "Jaiprakash Associates Limited", "category": "Real Estate Builders & Construction Company", "street": "63, J House, Basant Lok, Vasant Vihar,", "city": "New Delhi, Delhi 110057", "phone": "01149828500", "website": "http://www.jalindia.com/", "rating": 4.4, "review_count": "", "latitude": 28.557187, "longitude": 77.167068, "maps_url": "https://www.google.com/maps/place/?q=place_id:0x390d1dbc6fffffff:0x470ee9dfa48102cf"}, {"place_id": "0x390d1d3422c4b133:0x37f83955520b4be5", "name": "Liveup Homes Construction Company", "category": "Real Estate Builders & Construction Company", "street": "Second floor, L-92, Munirka", "city": "Outer Ring Rd", "phone": "09810814484", "website": "https://liveup.in/", "rating": 4.9, "review_count": "", "latitude": 28.5563354, "longitude": 77.17473249999999, "maps_url": "https://www.google.com/maps/place/?q=place_id:0x390d1d3422c4b133:0x37f83955520b4be5"}, {"place_id": "0xa3f7b500ba6bee9b:0xbf6f44de92b28de", "name": "Yuvocreations Private Limited ( \u092f\u0941\u0935\u094b\u0915\u094d\u0930\u093f\u090f\u0936\u0928\u094d\u0938 \u092a\u094d\u0930\u093e\u0907\u0935\u0947\u091f \u0932\u093f\u092e\u093f\u091f\u0947\u0921 ) - Website Designing & Digital Marketing Agency", "category": "Software company", "street": "Lane no.4", "city": "Khasra no. 258, Westend Marg", "phone": "07042123166", "website": "https://yuvocreations.com/", "rating": 5, "review_count": "", "latitude": 28.5169774, "longitude": 77.19925789999999, "maps_url": "https://www.google.com/maps/place/?q=place_id:0xa3f7b500ba6bee9b:0xbf6f44de92b28de"}, {"place_id": "0x390d1dd455555555:0xf0c0ae7cb8e85b43", "name": "AtoZ Group of Companies", "category": "Property management company", "street": "37/537, Vasant Kunj Rd", "city": "Block A, Mahipalpur Village, Mahipalpur", "phone": "09810818888", "website": "http://www.atozgroup.in/", "rating": 3.7, "review_count": "", "latitude": 28.5452659, "longitude": 77.128058, "maps_url": "https://www.google.com/maps/place/?q=place_id:0x390d1dd455555555:0xf0c0ae7cb8e85b43"}, {"place_id": "0x331745c76a06d77:0x3f5c561237cb7a3e", "name": "Webreachpro Technologies", "category": "Marketing agency", "street": "Phase-2", "city": "25B", "phone": "09643014632", "website": "https://webreachpro.in/", "rating": 5, "review_count": "", "latitude": 28.5415092, "longitude": 77.1842592, "maps_url": "https://www.google.com/maps/place/?q=place_id:0x331745c76a06d77:0x3f5c561237cb7a3e"}, {"place_id": "0xac577056c2b5ff3d:0xaf00253141553d04", "name": "Devnotam | IT Company", "category": "Internet marketing service", "street": "", "city": "", "phone": "", "website": "https://devnotam.com/", "rating": 5, "review_count": "", "latitude": 28.692404999999997, "longitude": 77.090042, "maps_url": "https://www.google.com/maps/place/?q=place_id:0xac577056c2b5ff3d:0xaf00253141553d04"}, {"place_id": "0x390cfb4bf15a6733:0xaf50e6f3c5fb7641", "name": "Digitals Daddy: Web & App Development Company", "category": "Software company", "street": "Metro Gate No. 2", "city": "Nearest Sikandarpur", "phone": "09818286609", "website": "https://www.digitalsdaddy.com/", "rating": 4.9, "review_count": "", "latitude": 28.4847884, "longitude": 77.0922192, "maps_url": "https://www.google.com/maps/place/?q=place_id:0x390cfb4bf15a6733:0xaf50e6f3c5fb7641"}, {"place_id": "0x390d05677ee3aecd:0xa51743b53fa39187", "name": "Weblife Infotech Pvt Ltd (Destech Media)", "category": "Software company", "street": "", "city": "", "phone": "07042569776", "website": "http://www.weblifeindia.in/", "rating": 2.9, "review_count": "", "latitude": 28.5273522, "longitude": 77.20898509999999, "maps_url": "https://www.google.com/maps/place/?q=place_id:0x390d05677ee3aecd:0xa51743b53fa39187"}, {"place_id": "0x390d193c3a36e523:0xe68f8d2568faeaad", "name": "Espire Infolabs Pvt. Ltd.", "category": "Software company", "street": "486 & 487", "city": "Phase III, Udyog Vihar III, Sector 20", "phone": "01247173000", "website": "http://www.espire.com/", "rating": 4.1, "review_count": "", "latitude": 28.5119516, "longitude": 77.0899661, "maps_url": "https://www.google.com/maps/place/?q=place_id:0x390d193c3a36e523:0xe68f8d2568faeaad"}, {"place_id": "0x390d1dbb09751a4b:0x1eae8e09d7c6e5a9", "name": "Peer Share #Coworking #Business Centre", "category": "Coworking space", "street": "35, Munirka Marg", "city": "Basant Lok, Vasant Vihar", "phone": "09911044445", "website": "https://peersharecoworking.com/", "rating": 4.2, "review_count": "", "latitude": 28.558162199999998, "longitude": 77.1640417, "maps_url": "https://www.google.com/maps/place/?q=place_id:0x390d1dbb09751a4b:0x1eae8e09d7c6e5a9"}, {"place_id": "0x61679272b097afaf:0x2d8ff2b0d95a1e18", "name": "Busybots | RPA & Robotic Process Automation for Banking, Healthcare, AI Services & UiPath, Python Training in Delhi", "category": "Software company", "street": "1st Floor, D", "city": "25, 100 Feet Rd", "phone": "09315867465", "website": "https://www.busybots.in/", "rating": 5, "review_count": "", "latitude": 28.5055157, "longitude": 77.1852263, "maps_url": "https://www.google.com/maps/place/?q=place_id:0x61679272b097afaf:0x2d8ff2b0d95a1e18"}, {"place_id": "0x390d1f0df92e353d:0x54e79553d987073c", "name": "Zombie Marketers | Performance Marketing | Digital Marketing | Website development company in Delhi | SEO company in Delhi", "category": "Marketing agency", "street": "89/9 Mamman House B Block 4th Floor", "city": "Kishangarh Village, Vasant Kunj", "phone": "08527273938", "website": "", "rating": 4.4, "review_count": "", "latitude": 28.5189249, "longitude": 77.1646754, "maps_url": "https://www.google.com/maps/place/?q=place_id:0x390d1f0df92e353d:0x54e79553d987073c"}, {"place_id": "0x390d1d140d4a3957:0x8b270860b8fbfb7f", "name": "XPLORE BROADBAND", "category": "Internet service provider", "street": "217C", "city": "near Baba Bekary", "phone": "09953500424", "website": "", "rating": 2.8, "review_count": "", "latitude": 28.551422, "longitude": 77.1700824, "maps_url": "https://www.google.com/maps/place/?q=place_id:0x390d1d140d4a3957:0x8b270860b8fbfb7f"}, {"place_id": "0x390d1dcc2af98305:0x3a2256908388d2bd", "name": "Indus Towers Ltd", "category": "Back Office", "street": "1, Aravali Crescent", "city": "Nelson Mandela Marg", "phone": "01244296766", "website": "https://www.industowers.com/", "rating": 3.8, "review_count": "", "latitude": 28.5399893, "longitude": 77.154032, "maps_url": "https://www.google.com/maps/place/?q=place_id:0x390d1dcc2af98305:0x3a2256908388d2bd"}, {"place_id": "0x390d1b0010fc2321:0x12e9154c815cf007", "name": "Prashant Dwivedi IT company", "category": "Warehouse", "street": "G3P5+GVC", "city": "Nayak Pura, Bijwasan", "phone": "", "website": "", "rating": "", "review_count": "", "latitude": 28.536316, "longitude": 77.059649, "maps_url": "https://www.google.com/maps/place/?q=place_id:0x390d1b0010fc2321:0x12e9154c815cf007"}, {"place_id": "0x390d19345bcdc4f3:0x61d5221ed2c17f35", "name": "Cognizant", "category": "Software company", "street": "Tower C, SEZ Building, Building No 6, 5th & 6th Floor DLF C yber City Rd W Block", "city": "Near Shankar Chowk", "phone": "", "website": "http://www.cognizant.com/india", "rating": 4.1, "review_count": "", "latitude": 28.4964521, "longitude": 77.096576, "maps_url": "https://www.google.com/maps/place/?q=place_id:0x390d19345bcdc4f3:0x61d5221ed2c17f35"}, {"place_id": "0x390d1d8baaaaaaab:0x81e02841f207d0f0", "name": "S SONY & COMPANY PVT. LTD", "category": "Real Estate Builders & Construction Company", "street": "G-4, ANUPAMA BUILDING II FLOOR", "city": "Hauz Khas", "phone": "01135002651", "website": "http://ssony.in/", "rating": 4.9, "review_count": "", "latitude": 28.5510508, "longitude": 77.2048471, "maps_url": "https://www.google.com/maps/place/?q=place_id:0x390d1d8baaaaaaab:0x81e02841f207d0f0"}, {"place_id": "0x390d193c3a36fabd:0x8bd7aacd8793bdb7", "name": "Orange Business Services", "category": "Public relations firm", "street": "Infinity Tower 8, Tower B", "city": "DLF Cyber City, DLF Phase 2, Sector 25", "phone": "", "website": "http://www.orange-business.com/", "rating": 4.5, "review_count": "", "latitude": 28.495814199999998, "longitude": 77.0910088, "maps_url": "https://www.google.com/maps/place/?q=place_id:0x390d193c3a36fabd:0x8bd7aacd8793bdb7"}, {"place_id": "0x390d1d1cfb866583:0x2bad9ebc0a990b11", "name": "RankFast", "category": "Marketing agency", "street": "26, LGF", "city": "D6 St", "phone": "09711945770", "website": "https://rankfast.co/", "rating": 4.8, "review_count": "", "latitude": 28.5620388, "longitude": 77.15334419999999, "maps_url": "https://www.google.com/maps/place/?q=place_id:0x390d1d1cfb866583:0x2bad9ebc0a990b11"}, {"place_id": "0xaeeb0801ae614225:0xd9da139ae362a39c", "name": "ONE COUNSEL", "category": "Legal services", "street": "Third Floor", "city": "352 E/5", "phone": "09555506208", "website": "https://www.onecounselindia.com/", "rating": 4.8, "review_count": "", "latitude": 28.5523141, "longitude": 77.16922439999999, "maps_url": "https://www.google.com/maps/place/?q=place_id:0xaeeb0801ae614225:0xd9da139ae362a39c"}, {"place_id": "0x61b1b57a323cb4cf:0xdcccbd8cc06c7739", "name": "Warranium Energy Private Limited", "category": "Sewage treatment plant", "street": "213-B, Nelson Mandela Marg", "city": "Munirka", "phone": "09871625535", "website": "https://warranium.com/", "rating": 5, "review_count": "", "latitude": 28.5582139, "longitude": 77.1698425, "maps_url": "https://www.google.com/maps/place/?q=place_id:0x61b1b57a323cb4cf:0xdcccbd8cc06c7739"}, {"place_id": "0x390d1d001a191f6f:0x17a7c404f2ddad64", "name": "Design Unlimited", "category": "Graphic designer", "street": "Paal Dairy", "city": "352/ E/4, Baba Gang Nath Marg", "phone": "08587890064", "website": "https://designunlimited.in/", "rating": 5, "review_count": "", "latitude": 28.552744399999998, "longitude": 77.1695331, "maps_url": "https://www.google.com/maps/place/?q=place_id:0x390d1d001a191f6f:0x17a7c404f2ddad64"}, {"place_id": "0x390d1d22ae67f8f3:0x7e04eef96598ad98", "name": "India Tour And Travels", "category": "Travel agency", "street": "C-252, Kusumpur", "city": "Village", "phone": "09582204861", "website": "", "rating": 4.8, "review_count": "", "latitude": 28.5539463, "longitude": 77.15499319999999, "maps_url": "https://www.google.com/maps/place/?q=place_id:0x390d1d22ae67f8f3:0x7e04eef96598ad98"}, {"place_id": "0x390ce36b6cccfa4d:0x5f1701ff9b7f71d7", "name": "Ambizen India - python java c++ programming coding classes courses coaching institute freshers beginners near me delhi noida", "category": "Software Training Institute", "street": "D-3/211, 1st Floor", "city": "Upstairs Of Bank Of Baroda", "phone": "09007144778", "website": "https://www.ambizenindia.in/", "rating": 4.9, "review_count": "", "latitude": 28.5576458, "longitude": 77.17269499999999, "maps_url": "https://www.google.com/maps/place/?q=place_id:0x390ce36b6cccfa4d:0x5f1701ff9b7f71d7"}, {"place_id": "0x49b34d99c3eaa061:0x2e4d82fbe33431c7", "name": "Nari Nyay Advocates", "category": "Legal services", "street": "Hill View Apartments", "city": "B-33", "phone": "", "website": "https://form.typeform.com/to/FyCYyoyy", "rating": 5, "review_count": "", "latitude": 28.550077899999998, "longitude": 77.1596382, "maps_url": "https://www.google.com/maps/place/?q=place_id:0x49b34d99c3eaa061:0x2e4d82fbe33431c7"}, {"place_id": "0x390d1d94f23d028b:0x97ac997954aadc35", "name": "Ca Atul Mangal & Co", "category": "Chartered accountant", "street": "19, Flat", "city": "Block A", "phone": "09212007566", "website": "http://www.camangal.com/", "rating": 4.9, "review_count": "", "latitude": 28.553198599999998, "longitude": 77.1762256, "maps_url": "https://www.google.com/maps/place/?q=place_id:0x390d1d94f23d028b:0x97ac997954aadc35"}, {"place_id": "0x390ce1be2d2a7377:0x5020cce4790298e1", "name": "AJWA KAIF PVT LTD", "category": "Computer support and services", "street": "Ground Floor", "city": "Khirki Vill", "phone": "01142502100", "website": "https://www.ajwakaif.com/", "rating": 5, "review_count": "", "latitude": 28.5309287, "longitude": 77.2194186, "maps_url": "https://www.google.com/maps/place/?q=place_id:0x390ce1be2d2a7377:0x5020cce4790298e1"}, {"place_id": "0x390ce15795555555:0x9bb8a801d00d7573", "name": "DreamSoft Infotech - Website Development Company in India", "category": "Software company", "street": "A-75 Third Floor", "city": "A Block, Sector 5", "phone": "01204380622", "website": "https://dreamsoftinfotech.com/", "rating": 3.4, "review_count": "", "latitude": 28.591018899999998, "longitude": 77.32201529999999, "maps_url": "https://www.google.com/maps/place/?q=place_id:0x390ce15795555555:0x9bb8a801d00d7573"}, {"place_id": "0x390d1c1375428d95:0x329a5350d2f550ec", "name": "Global India Express Pvt Ltd", "category": "Corporate office", "street": "L-204, Street Number 7C", "city": "near Vijaya Bank", "phone": "09810497982", "website": "https://www.globalindiaexpress.com/", "rating": 4.6, "review_count": "", "latitude": 28.544389499999998, "longitude": 77.1232125, "maps_url": "https://www.google.com/maps/place/?q=place_id:0x390d1c1375428d95:0x329a5350d2f550ec"}, {"place_id": "0x390d1dc92e3c3dbf:0x4b4acd2dae35e5fb", "name": "Entertainment Design Company EDC", "category": "Invitation printing service", "street": "426, Third Floor, DLF Emporio", "city": "Nelson Mandela Marg", "phone": "01141349001", "website": "http://www.edc.co.in/", "rating": 3.3, "review_count": "", "latitude": 28.543563, "longitude": 77.156797, "maps_url": "https://www.google.com/maps/place/?q=place_id:0x390d1dc92e3c3dbf:0x4b4acd2dae35e5fb"}, {"place_id": "0x390d1d873a26de89:0xbb1717939a0a1b6", "name": "Indian round trips", "category": "Travel agency", "street": "Nelson Mandela Marg", "city": "Munirka Vihar, Munirka", "phone": "08962070102", "website": "", "rating": 5, "review_count": "", "latitude": 28.5534115, "longitude": 77.1669105, "maps_url": "https://www.google.com/maps/place/?q=place_id:0x390d1d873a26de89:0xbb1717939a0a1b6"}, {"place_id": "0x390d1d8c3bc9c68d:0xf71204a70007ed24", "name": "Hitachi India Pvt. Ltd. & Hitachi Lift India Pvt Ltd", "category": "Manufacturer", "street": "H42C+6GH, Indira Gandhi International Airport", "city": "Tower B", "phone": "01140605252", "website": "http://www.hitachi.co.in/", "rating": 1.4, "review_count": "", "latitude": 28.550555499999998, "longitude": 77.1213703, "maps_url": "https://www.google.com/maps/place/?q=place_id:0x390d1d8c3bc9c68d:0xf71204a70007ed24"}, {"place_id": "0x390d1da5ae132195:0xc1de3fcb94a46da1", "name": "Ambika Telecom", "category": "Computer support and services", "street": "66-C, 3rd Floor, Hans Bhawan", "city": "opposite Canara Bank", "phone": "09810367004", "website": "", "rating": 4.7, "review_count": "", "latitude": 28.555113199999997, "longitude": 77.1745993, "maps_url": "https://www.google.com/maps/place/?q=place_id:0x390d1da5ae132195:0xc1de3fcb94a46da1"}, {"place_id": "0x390cfb6f5f355171:0x293ef389560eaf8a", "name": "Solis Tractors", "category": "Corporate office", "street": "TERI UNIVERSITY", "city": "Plot No. 10", "phone": "01166455200", "website": "https://www.solisworld.com/", "rating": 4.5, "review_count": "", "latitude": 28.5447602, "longitude": 77.14801829999999, "maps_url": "https://www.google.com/maps/place/?q=place_id:0x390cfb6f5f355171:0x293ef389560eaf8a"}, {"place_id": "0x3be7c21b5901e181:0x7fe794585addc1f6", "name": "Smartinfologiks - Software Development Company in India | IT Solutions", "category": "Software company", "street": "Hilton Center", "city": "514", "phone": "07400064691", "website": "https://www.smartinfologiks.com/", "rating": 4.6, "review_count": "", "latitude": 19.0139592, "longitude": 73.0382705, "maps_url": "https://www.google.com/maps/place/?q=place_id:0x3be7c21b5901e181:0x7fe794585addc1f6"}, {"place_id": "0x390d19482ec7af6b:0xce48ba6ad2474bf2", "name": "AVIZVA Solutions Pvt Ltd", "category": "Corporate office", "street": "16th Floor, Building No. 14 Tower D Building", "city": "DLF Cyber City, DLF Phase 3, Sector 25A", "phone": "01246542490", "website": "http://www.avizva.com/", "rating": 3.9, "review_count": "", "latitude": 28.496678799999998, "longitude": 77.0944262, "maps_url": "https://www.google.com/maps/place/?q=place_id:0x390d19482ec7af6b:0xce48ba6ad2474bf2"}, {"place_id": "0x3bc2becdc35b6937:0x515ac559c349eee3", "name": "Thinkitive Technologies Private Limited", "category": "Software company", "street": "4th Floor", "city": "ABIL IMPERIAL COMMERCIAL SPACES", "phone": "08956467327", "website": "https://www.thinkitive.com/", "rating": 3.9, "review_count": "", "latitude": 18.5563888, "longitude": 73.7729748, "maps_url": "https://www.google.com/maps/place/?q=place_id:0x3bc2becdc35b6937:0x515ac559c349eee3"}, {"place_id": "0x390d1db6a92a7f7f:0xfed699d21f8c2d51", "name": "Migvisa Services | Best visa Consultant in Delhi | Tourist Visa & Business, Study Visa.", "category": "Visa Agent", "street": "Office No.7", "city": "Market, Nelson Mandela Marg", "phone": "09810481174", "website": "", "rating": 4.5, "review_count": "", "latitude": 28.5546336, "longitude": 77.1669491, "maps_url": "https://www.google.com/maps/place/?q=place_id:0x390d1db6a92a7f7f:0xfed699d21f8c2d51"}]}